Workbook
Name NativeTimeline_Order_Date: #N/A
Name Sales_Data: REFERENCE!$C$60
Name Slicer_Brand: #N/A
Name Slicer_Category: #N/A
Name Slicer_Category1: #N/A
Name Slicer_City: #N/A
Name Slicer_Full_Time_Result: #N/A
Name Slicer_Home_Team: #N/A
Name Slicer_League: #N/A
Name Slicer_Notes: #N/A
Name Slicer_Payment_Method: #N/A
Name Slicer_Product: #N/A
Name Slicer_Region: #N/A
Name Slicer_Salesperson: #N/A
Name Slicer_Season: #N/A
Name Slicer_Stadium: #N/A

Sheet Sheet1
A1: Branch | B1: Region | C1: Revenue (Rs.) | D1: Cost (Rs.) | E1: Profit (Rs.) | F1: Manager | G1: Confidential Notes
A2: Branch C | B2: East | C2: 610000 | D2: 510000 | E2: 100000 | F2: Simran Kaur | G2: Under review
A3: Branch A | B3: North | C3: 850000 | D3: 620000 | E3: 230000 | F3: Karan Malhotra | G3: Lease renewal pending
A4: Branch B | B4: South | C4: 920000 | D4: 640000 | E4: 280000 | F4: Divya Krishnan | G4: Staff shortage Q3
A5: Branch D | B5: West | C5: 1050000 | D5: 700000 | E5: 350000 | F5: Farah Khan | G5: Top performer

Sheet Sheet2
A1: Category | B1: Week 1 | C1: Week 2 | D1: Week 3 | E1: Week 4 | F1: TOTAL | G1: AVERAGE
A2: Groceries | B2: 2200 | C2: 1950 | D2: 2400 | E2: 2100 | F2: =SUM(B2:E2) -> 8650 | G2: =AVERAGE(B2:E2) -> 2162.5
A3: Transport | B3: 800 | C3: 750 | D3: 900 | E3: 820 | F3: =SUM(B3:E3) -> 3270 | G3: =AVERAGE(B3:E3) -> 817.5
A4: Utilities | B4: 1500 | C4: 1500 | D4: 1600 | E4: 1550 | F4: =SUM(B4:E4) -> 6150 | G4: =AVERAGE(B4:E4) -> 1537.5
A5: Entertainment | B5: 600 | C5: 900 | D5: 400 | E5: 750 | F5: =SUM(B5:E5) -> 2650 | G5: =AVERAGE(B5:E5) -> 662.5
A6: Miscellaneous | B6: 350 | C6: 500 | D6: 300 | E6: 450 | F6: =SUM(B6:E6) -> 1600 | G6: =AVERAGE(B6:E6) -> 400
A7: TOTAL | B7: =SUM(B2:B6) -> 5450 | C7: =SUM(C2:C6) -> 5600 | D7: =SUM(D2:D6) -> 5600 | E7: =SUM(E2:E6) -> 5670 | F7: =SUM(B7:E7) -> 22320

Sheet Sheet3
A1: A: Roll No. | B1: B: Week Start Date | C1: C: Month | D1: D: Quarter Label | E1: E: Odd Numbers | F1: F: Invoice No.
A2: 1 | B2: 46272 | C2: January | D2: Q1 | E2: 1 | F2: INV-001
A3: 2 | B3: 46279 | C3: February | D3: Q2 | E3: 3 | F3: INV-002
A4: 3 | B4: 46286 | C4: March | D4: Q3 | E4: 5 | F4: INV-003
A5: 4 | B5: 46293 | C5: April | D5: Q4 | E5: 7 | F5: INV-004
A6: 5 | B6: 46300 | C6: May | D6: Q1 | E6: 9 | F6: INV-005
A7: 6 | B7: 46307 | C7: June | D7: Q2 | E7: 11 | F7: INV-006
A8: 7 | B8: 46314 | C8: July | D8: Q3 | E8: 13 | F8: INV-007

Sheet Sheet4
A1: Full Name | B1: First Name (Q1) | C1: Last Name (Q1) | D1: Email | E1: Username (Q2) | F1: Phone (raw) | G1: Phone Formatted (Q3) | H1: Initials
A2: Nikhil Rane | B2: Nikhil | C2: Rane | D2: nikhil.rane@gmail.com | E2: nikhil.rane | F2: 9876543210 | G2: +91-98765-43210' | H2: N.R
A3: Sarah Mathew | B3: Sarah | C3: Mathew | D3: sarah.mathew@outlook.com | E3: sarah.mathew | F3: 9123456780 | G3: +91-91234-56780' | H3: S.M
A4: Farhan Sheikh | B4: Farhan | C4: Sheikh | D4: farhan.sheikh@yahoo.co.in | E4: farhan.sheikh | F4: 9988776655 | G4: +91-99887-76655' | H4: F.S
A5: Divya Krishnan | B5: Divya | C5: Krishnan | D5: divya.krishnan@gmail.com | E5: divya.krishnan | F5: 9012345678 | G5: +91-90123-45678' | H5: D.K
A6: Om Prakash | B6: Om | C6: Prakash | D6: om.prakash@companymail.com | E6: om.prakash | F6: 9765432109 | G6: +91-97654-32109' | H6: O.P

Sheet Sheet5
A1: Roll No. | B1: Student Name | C1: Grade Level | D1: Marks | E1: Subject | F1: Attendance %
A2: 1 | B2: Kabir Singh | C2: A | D2: 81 | E2: Maths | F2: 88
A3: 10 | B3: Arjun Bose | C3: A | D3: 67 | E3: Science | F3: 90
A4: 12 | B4: Rohan Mehta | C4: A | D4: 34 | E4: Science | F4: 78
A5: 4 | B5: Diya Menon | C5: B | D5: 96 | E5: Maths | F5: 60
A6: 5 | B6: Ishita Kapoor | C6: B | D6: 73 | E6: Science | F6: 92
A7: 15 | B7: Meera Pillai | C7: B | D7: 40 | E7: Science | F7: 95
A8: 8 | B8: Aditya Verma | C8: C | D8: 96 | E8: Maths | F8: 65
A9: 7 | B9: Ananya Das | C9: C | D9: 88 | E9: Maths | F9: 55

Sheet Sheet6
A1: Tax Rate: | B1: 0.18
A3: Item | B3: Quantity | C3: Unit Cost | D3: Line Total | E3: Tax @ Rate | F3: Grand Total
A4: Chairs | B4: 20 | C4: 1200 | D4: 24000 | E4: =D4*B$1 -> 4320 | F4: 28320
A5: Tables | B5: 10 | C5: 3500 | D5: 35000 | E5: =D5*B$1 -> 6300 | F5: 41300
A6: Cabinets | B6: 5 | C6: 8000 | D6: 40000 | E6: =D6*B$1 -> 7200 | F6: =D6+E6 -> 47200
A7: Shelves | B7: 15 | C7: 950 | D7: 14250 | E7: =D7*B$1 -> 2565 | F7: 16815

Sheet Sheet7
A1: Total Revenue (Rs.): | B1: =SUM(D6:D25) -> 194430
A2: Total Profit (Rs.): | B2: =SUM(E6:E25) -> 45638
A3: Average Order Value (Rs.): | B3: 9147.6
A5: Order ID | B5: Customer | C5: Region | D5: Amount (Rs.) | E5: Profit (Rs.)
A6: ORD-200 | B6: Deepak Joshi | C6: West | D6: 9700 | E6: 1412
A7: ORD-201 | B7: Deepak Joshi | C7: South | D7: 20333 | E7: 9000
A8: ORD-202 | B8: Deepak Joshi | C8: West | D8: 5025 | E8: 900
A9: ORD-203 | B9: Deepak Joshi | C9: South | D9: 12319 | E9: 1848
A10: ORD-204 | B10: Farah Khan | C10: East | D10: 3800 | E10: 9876
A11: ORD-205 | B11: Ravi Kumar | C11: North | D11: 4323 | E11: 900
A12: ORD-206 | B12: Farah Khan | C12: West | D12: 11755 | E12: 2000
A13: ORD-207 | B13: Kavita Menon | C13: South | D13: 12713 | E13: 1907
A14: ORD-208 | B14: Ravi Kumar | C14: North | D14: 12209 | E14: 1831
A15: ORD-209 | B15: Ravi Kumar | C15: South | D15: 2975 | E15: 446
A16: ORD-210 | B16: Deepak Joshi | C16: North | D16: 5963 | E16: 894
A17: ORD-211 | B17: Farah Khan | C17: East | D17: 14748 | E17: 2212
... A25: ORD-219 | B25: Ravi Kumar | C25: North | D25: 2487 | E25: 999

Sheet IS functions
B1: ISBLANK(value)
B2: If a cell is blank, it returns TRUE.
B3: If a cell is not blank, it returns FALSE.
B5: Values | C5: Formulas
B6: Orange
B7: TRUE | C7: =ISBLANK(B7) -> FALSE
B8: FALSE | C8: =ISBLANK(B8) -> FALSE
C9: =ISBLANK(B9) -> TRUE
C10: =ISBLANK(B10) -> FALSE
B11: King Cobra | C11: =ISBLANK(B11) -> FALSE
B14: ISERR(value)
B15: Checks whether a value is an error (#VALUE!, #REF!, #DIV/0!, #NUM!, #NAME?, or #NULL!) excluding #N/A, and returns TRUE or FALSE
B17: Values | C17: Formula
B18: #VALUE! | C18: =ISERR(B18) -> TRUE
B19: #REF! | C19: =ISERR(B19) -> TRUE
B20: #DIV/0! | C20: =ISERR(B20) -> TRUE
B21: #NUM! | C21: =ISERR(B21) -> TRUE
B22: #NAME? | C22: =ISERR(B22) -> TRUE
B23: #NULL! | C23: =ISERR(B23) -> TRUE
B24: #N/A | C24: =ISERR(B24) -> FALSE
B25: Apple | C25: =ISERR(B25) -> FALSE
B28: ISERROR(value)
B29: Checks whether a value is an error (#N/A, #VALUE!, #REF!, #DIV/0!, #NUM!, #NAME?, or #NULL!), and returns TRUE or FALSE
B31: Values | C31: Formula
B32: #VALUE! | C32: =ISERROR(B32) -> TRUE
B33: #REF! | C33: =ISERROR(B33) -> TRUE
B34: #DIV/0! | C34: =ISERROR(B34) -> TRUE
B35: #NUM! | C35: =ISERROR(B35) -> TRUE
B36: #NAME? | C36: =ISERROR(B36) -> TRUE
B37: #NULL! | C37: =ISERROR(B37) -> TRUE
B38: #N/A | C38: =ISERROR(B38) -> TRUE
B39: Apple | C39: =ISERROR(B39) -> FALSE
B42: ISEVEN(value)
B43: Retursn TRUE if the number is even
B45: Values | C45: Formula
B46: 5 | C46: =ISEVEN(B46) -> FALSE
B47: 10 | C47: =ISEVEN(B47) -> TRUE
B48: 81/9 | C48: =ISEVEN(B48) -> #VALUE!
B49: Excel 2013 | C49: =ISEVEN(B49) -> #VALUE!
B52: ISODD(value)
B53: Retursn TRUE if the number is odd
B55: Values | C55: Formula
B56: 5 | C56: =ISODD(B56) -> TRUE
B57: 10 | C57: =ISODD(B57) -> FALSE
B58: 81/9 | C58: =ISODD(B58) -> #VALUE!
B59: Excel 2013 | C59: =ISODD(B59) -> #VALUE!
B62: ISFORMULA(value)
B63: Checks whether a reference is to a cell containing a formula, and returns TRUE or FALSE
B65: Values | C65: Formula
B66: =TODAY() -> 46312 | C66: =_xlfn.ISFORMULA(B66) -> TRUE
B67: 42308 | C67: =_xlfn.ISFORMULA(B67) -> FALSE
B68: =NOW() -> 46312.447 | C68: =_xlfn.ISFORMULA(B68) -> TRUE
B69: Kawser Ahmed | C69: =_xlfn.ISFORMULA(B69) -> FALSE
B70: Marissa Kawser | C70: =_xlfn.ISFORMULA(B70) -> FALSE
B73: ISLOGICAL(value)
B74: Checks whether a values is a logical value (TRUE or FALSE), and returns TRUE or FALSE
B76: Values | C76: Formula
B77: TRUE | C77: =ISLOGICAL(B77) -> TRUE
B78: FALSE | C78: =ISLOGICAL(B78) -> TRUE
B79: "TRUE" | C79: =ISLOGICAL(B79) -> FALSE
C80: =ISLOGICAL(B77=B78) -> TRUE
B83: ISNA(value)
B84: Checks whether a value is #N/A, and returns TRUE or FALSE
B86: Values | C86: Formula
B87: #VALUE! | C87: =ISNA(B87) -> FALSE
B88: #REF! | C88: =ISNA(B88) -> FALSE
B89: #NAME? | C89: =ISNA(B89) -> FALSE
B90: #N/A | C90: =ISNA(B90) -> TRUE
B93: ISNUMBER(value)
B94: Checks whether a value is a number, and returns TRUE or FALSE
B96: Values | C96: Formula
B97: Text | C97: =ISNUMBER(B97) -> FALSE
B98: 15 | C98: =ISNUMBER(B98) -> TRUE
B99: #VALUE! | C99: =ISNUMBER(B99) -> FALSE
B100: 89 | C100: =ISNUMBER(B100) -> TRUE
B101: 46267 | C101: =ISNUMBER(B101) -> TRUE
B104: ISREF(value)
B105: Checks whether a value is a reference, and returns TRUE or FALSE
B107: Values | C107: Formula
C108: =ISREF(B1) -> TRUE
C109: =ISREF(B1:B10) -> TRUE
C110: =ISREF(B1:D4 C1:C5) -> TRUE
C111: FALSE
C112: =ISREF( INDIRECT( "B1" ) ) -> TRUE
B115: ISTEXT(value)
B116: Checks whether a value is text, and returns TRUE or FALSE
B118: Values | C118: Formula
B119: Excel 2013 | C119: =ISTEXT(B119) -> TRUE
B120: 21 Wise Men | C120: =ISTEXT(B120) -> TRUE
B121: #VALUE! | C121: =ISTEXT(B121) -> FALSE
B122: 45 | C122: =ISTEXT(B122) -> FALSE
B125: ISNONTEXT(value)
B126: Checks whether a value is not text (blank cells are not text), and returns TRUE or FALSE
B128: Values | C128: Formula
B129: TRUE | C129: =ISNONTEXT(B129) -> TRUE
B130: Peter | C130: =ISNONTEXT(B130) -> FALSE
B131: 55 | C131: =ISNONTEXT(B131) -> TRUE
B132: #VALUE! | C132: =ISNONTEXT(B132) -> TRUE

Sheet Mathematical
B2: SUM(number1, [number2], [number3], [number4], …)
B3: Adds all the numbers in a range of cells
B5: Values | C5: Formula
B6: -5 | C6: =SUM(B6:B11) -> 40
B7: 15 | C7: =SUM(B6:B8,"5",TRUE,FALSE) -> 46
B8: 30
B9: 5
B10: TRUE
B11: FALSE
B14: AVERAGE(number1, [number2], [number3], [number4], …)
B15: Returns the average (arithmetic means) of its arguments, which can be numbers or names, arrays, or references that contain numbers
B17: Values | C17: Formula
B18: -5 | C18: =AVERAGE(B18:B23) -> 13.333333
B19: 15 | C19: =AVERAGE(B18:B20,"5",TRUE,FALSE) -> 7.6666667
B20: 30
B21: 5
B22: TRUE
B23: FALSE
B26: AVERAGEA(value1, [value2], [value3], [value4], …)
B27: Returns the average (arithmetic means) of its arguments, evaluating text and FALSE in arguments as 0; TRUE evaluates as 1. Arguments can be numbers, names, arrays, or references.
B29: Values | C29: Formula
B30: -5 | C30: =AVERAGEA(B30:B35) -> 6.8333333
B31: 15 | C31: =AVERAGEA(B30:B32,"5",TRUE,FALSE) -> 7.6666667
B32: 30
B33: 5
B34: TRUE
B35: FALSE
B37: COUNT(value1, [value2], [value3], …)
B38: Counts the number of cells in a range that contain numbers
B40: Values | C40: Formula
B41: -5 | C41: =COUNT(B41:B46) -> 3
B42: 15 | C42: =COUNT(B41:B43,"5",TRUE,FALSE) -> 6
B43: 30
B44: 5
B45: TRUE
B46: FALSE
B49: COUNTA(value1, [value2], [value3], …)
B50: Counts the number of cells in a range that are not empty
B53: Values | C53: Formula
B54: -5 | C54: =COUNTA(B54:B59) -> 6
B55: 15 | C55: =COUNTA(B54:B56,"5",TRUE,FALSE) -> 6
B56: 30
B58: TRUE
B59: FALSE
B62: MEDIAN(number1, [number2], [number3], …)
B63: Returns the median, or the number in the middle of the set of given numbers
B65: Data 1 | C65: Data 2
B66: 1 | C66: 15 | E66: =MEDIAN(B66:B72) -> 4
B67: 2 | C67: 10 | E67: =MEDIAN(B66:B73) -> 4.5
B68: 3 | C68: 5 | E68: =MEDIAN(C66:C72) -> 12
B69: 4 | C69: 8 | E69: =MEDIAN(C66:C73) -> 11
B70: 5 | C70: 12
B71: 6 | C71: 25
B72: 7 | C72: 13
B73: 8 | C73: 5
B76: SUMPRODUCT(array1, [array2], [array3], …)
B77: Retursn the sum of the products of corresponding ranges or arrays
B79: Sales Person | C79: Region | D79: Products | E79: Sales
B80: Jon | C80: West | D80: Apple | E80: 100
B81: Marissa | C81: East | D81: Orange | E81: 200 | G81: =SUMPRODUCT({4,5,6},{10,20,10}) -> 200
B82: Kawser | C82: East | D82: Banana | E82: 125 | G82: {=SUMPRODUCT(--(B80:B91="Jon"),--(C80:C91="West"),E80:E91)} -> 235
B83: Dipa | C83: West | D83: Banana | E83: 145
B84: Neri | C84: North | D84: Orange | E84: 45
B85: Jon | C85: South | D85: Apple | E85: 55
B86: Dipa | C86: West | D86: Apple | E86: 25
B87: Marissa | C87: East | D87: Orange | E87: 35
B88: Jon | C88: West | D88: Orange | E88: 50
B89: Kawser | C89: South | D89: Apple | E89: 60
B90: Marissa | C90: West | D90: Banana | E90: 75
B91: Jon | C91: West | D91: Apple | E91: 85
B94: SUMSQ(number1, [number2], [number3], …)
B95: Returns the sum of the squares of the arguments. The arguments can be numbers, arrays, names, or references to cells that contain numbers
B97: =SUMSQ(3,4,5) -> 50
B99: COUNTBLANK(range)
B100: Counts the number of empty cells in a range
B102: Values
B103: 5 | C103: =COUNTBLANK(B103:B109) -> 1
B104: 12
B105: 8
B107: 98
B109: Marissa
B112: EVEN(number)
B113: Rounds a positive number up and negative number down to the nearest even integer
B115: =EVEN(1.5) -> 2
B116: =EVEN(3) -> 4
B117: =EVEN(2) -> 2
B118: =EVEN(-1) -> -2
B121: ODD(number)
B122: Rounds a positive number up and negative number down to the nearest odd integer.
B124: =ODD(1.5) -> 3
B125: =ODD(3) -> 3
B126: =ODD(2) -> 3
B127: =ODD(-1) -> -1
B130: INT(number)
B131: Rounds a number down to the nearest integer
B133: =INT(8.9) -> 8
B134: =INT(-8.9) -> -9
B135: =INT(19.5) -> 19
B138: LARGE(array, k)
B139: Returns the k-th largest value in a data set. For example, the fifth largest number
...

Sheet FIND& SEARCH
B3: FIND(find_text, within_text, [start_num])
B4: Returns the starting position of one text string within another text string. FIND is case-sensitive
B6: Data | D6: =FIND("r",B7) -> 3
B7: Marissa Kawser Ron | D7: =FIND("r",B7,1) -> 3
D8: =FIND("r",B7,2) -> 3
D9: =FIND("r",B7,3) -> 3
D10: =FIND("r",B7,4) -> 14
D11: =FIND("R",B7) -> 16
B13: SEARCH(find_text, within_text, [start_num])
B14: Returns the number of the character at which a specific character or text string is first found, reading left to right (not case-sensitive)
B16: Data | D16: =SEARCH("r",B17) -> 3
B17: Marissa Kawser Ron | D17: =SEARCH("r",B17,1) -> 3
B18: "Jon" come here | D18: =SEARCH("r",B17,2) -> 3
B19: The "boss" is here | D19: =SEARCH("r",B17,3) -> 3
D20: =SEARCH("r",B17,4) -> 14
D21: =SEARCH("R",B17) -> 3
D22: =SEARCH(" ",B18) -> 6
D23: =SEARCH("""",B19) -> 5
B27: SUBSTITUTE(text, old_text, new_text, [instance_num])
B28: Replaces existing text with new text in a text string
B30: Data
B31: Quantity Sold Sold | C31: =SUBSTITUTE(B31,"Sold","bought") -> Quantity bought bought
B32: Year 2008 | C32: =SUBSTITUTE(B31,"Sold","bought",1) -> Quantity bought Sold
B33: Year 2009 | C33: =SUBSTITUTE(B31,"Sold","bought",2) -> Quantity Sold bought
C34: =SUBSTITUTE(B32,"08","13") -> Year 2013
B37: REPLACE(old_text, start_num, num_chars, new_text)
B38: Replaces part of a text string with different text string
B40: Data
B41: Marissa Khan | C41: =REPLACE(B41,9,1,"kawser") -> Marissa kawserhan
B42: 2015 | C42: =REPLACE(B41,9,2,"Kawser") -> Marissa Kawseran
B43: 9876543210 | C43: =REPLACE(B41,9,3,"Kawser") -> Marissa Kawsern
C44: =REPLACE(B41,9,4,"Kawser") -> Marissa Kawser
C45: =REPLACE(B41,1,1,"Kawser") -> Kawserarissa Khan
C46: =REPLACE(B41,2,2,"Kawser") -> MKawserissa Khan
C47: =REPLACE(B41,3,3,"Kawser") -> MaKawsersa Khan
C48: =REPLACE(B41,4,4,"Kawser") -> MarKawser Khan

Sheet Date & time
B2: DATE(year, month, day)
B3: Returns the number that represents the date in Microsoft Excel date-time code
B5: Year | C5: Month | D5: Day
B6: 2015 | C6: 10 | D6: 15 | F6: =DATE(B6,C6,D6) -> 42292
B7: 2010 | C7: 5 | D7: 25 | F7: =DATE(2010,C6,D6) -> 40466
B8: 1805 | C8: 8 | D8: 23 | F8: =DATE(B8,C8,D8) -> 659499
B12: DATEVALUE(date_text)
B13: Converts a date in the form of text to a number that represents the date in the Microsoft Excel date-time code
B15: =DATEVALUE("25/10/2015") -> 42302
B16: =DATEVALUE("22 May, 2015") -> 42146
B17: =DATEVALUE("22-May-2015") -> 42146
B20: TIME(hour, minute, second)
B21: Converts hours, minutes, and seconds given as numbers to an Excel serial number, formatted with a time format
B23: Hour | C23: Minute | D23: Second
B24: 12 | C24: 30 | D24: 30 | F24: =TIME(B24,C24,D24) -> 0.52118056
B25: 16 | C25: 45 | D25: 30 | F25: =TIME(B25,C25,D25) -> 0.69826389
B26: 16 | C26: 48 | D26: 15 | F26: =TIME(B26,C26,D26) -> 0.70017361
B29: TIMEVALUE(time_text)
B30: Converts a text time to an Excel serial number for a time, a number from 0 (12:00:00 AM) to 0.999988424 (11:59:59 PM). Format the number with a time format after entering the formula
B32: =TIMEVALUE("2:50 PM") -> 0.61805556
B33: =TIMEVALUE("22-AUGUST-2015 2:50 PM") -> 0.61805556
B36: NOW()
B37: Returns the current date and time formatted as a date and time
B39: =NOW() -> 46312.447
B40: =NOW()+7 -> 46319.447
B43: TODAY()
B44: Returns the current date formatted as a date
B46: =TODAY() -> 46312
B49: YEAR, MONTH, DAY, HOUR, MINUTE and SECOND Functions
B50: All of these functions take one argument: serial_number
B52: Function Name
B53: YEAR(…) | D53: =YEAR(NOW()) -> 2026
B54: MONTH(…) | D54: =MONTH(NOW()) -> 10
B55: DAY(…) | D55: =DAY(NOW()) -> 17
B56: HOUR(…) | D56: =HOUR(NOW()) -> 10
B57: MINUTE(…) | D57: =MINUTE(NOW()) -> 44
B58: SECOND(…) | D58: =SECOND(NOW()) -> 19
B62: WEEKDAY(serial_number, [return_type])
B63: Returns a number from 1 to 7 identifying the day of the week from a date
B65: =WEEKDAY(NOW()) -> 7
B66: =WEEKDAY(NOW(),16) -> 1
B70: DAYS(end_date, start_date)
B71: Returns the number of days between the two dates
B73: End Date | C73: Start Date | E73: =_xlfn.DAYS(B74,C74) -> 12531
B74: 42310 | C74: 29779 | E74: =_xlfn.DAYS("15-SEP-2026","6-JAN-2006") -> 7557
B78: NETWORKDAYS(start_date, end_date, [holidays])
B79: Returns the number of whole workdays between two dates
B81: Date | C81: Description
B82: 40918 | C82: Start date of project | F82: =NETWORKDAYS(B82,B83) -> 496
B83: 41611 | C83: End date of project | F83: =NETWORKDAYS(B82,B83,B84:B86) -> 493
B84: 41235 | C84: Holiday
B85: 41011 | C85: Holiday
B86: 41295 | C86: Holiday
B89: WORKDAY(start_date, days, [holidays])
B90: Returns the serial number of the date before or after a specified number of workdays
B92: Start Date | C92: 41945
B93: Days to Complete the work | C93: 200 | F93: =WORKDAY(C92,C93) -> 42223
B94: Holidays | C94: 42262 | D94: 41989 | E94: 41724 | F94: =WORKDAY(C92,C93,C94:E94) -> 42226

Sheet REFERENCE
B2: ADDRESS(row_num, column_num, [abs_num], [a1], [sheet_text])
B3: Creates a cell reference as text, given specified row and column numbers
C5: Formula | D5: Result
C6: =_xlfn.FORMULATEXT(D6) -> =ADDRESS(2,3) | D6: =ADDRESS(2,3) -> $C$2
C7: =_xlfn.FORMULATEXT(D7) -> =ADDRESS(2,3,2) | D7: =ADDRESS(2,3,2) -> C$2
C8: =_xlfn.FORMULATEXT(D8) -> =ADDRESS(2,3,2,FALSE) | D8: =ADDRESS(2,3,2,FALSE) -> R2C[3]
C9: =_xlfn.FORMULATEXT(D9) -> =ADDRESS(2,3,1,FALSE,"[Book1]Sheet1") | D9: =ADDRESS(2,3,1,FALSE,"[Book1]Sheet1") -> [Book1]Sheet1!R2C3
C10: =_xlfn.FORMULATEXT(D10) -> =ADDRESS(2,3,4,FALSE,"EXCEL SHEET") | D10: =ADDRESS(2,3,4,FALSE,"EXCEL SHEET") -> 'EXCEL SHEET'!R[2]C[3]
B13: CHOOSE(index_num, value1, [value2], [value3], …)
B14: Chooses a value or action to perform from a list of values, based on an index number
B16: Data | G16: Formula | H16: Result | I16: Remarks
B17: Marissa | D17: =CHOOSE(3,B17,B18,B19,B20,B21,B22,) -> Excel BI | G17: =_xlfn.FORMULATEXT(H17) -> =CHOOSE(3,B17,B18,B19,B20,B21,B22) | H17: =CHOOSE(3,B17,B18,B19,B20,B21,B22) -> Excel BI | I17: Value of the 3rd list argument (value of cell B23)
B18: Excel | D18: =CHOOSE(5,B17,B18,B19,B20,B21,B22,B22) -> Power Pivot | G18: =_xlfn.FORMULATEXT(H18) -> =CHOOSE(5,B17,B18,B19,B20,B21,B22) | H18: =CHOOSE(5,B17,B18,B19,B20,B21,B22) -> Power Pivot | I18: Value of the 5th list argument (value of cell B25)
B19: Excel BI
B20: Power Query
B21: Power Pivot
B22: Power Map
B25: Array Form: | C25: INDEX(array, row_num, [column_num])
B26: Return the value of a specified cell or array of cells
B27: Reference Form: | C27: INDEX(reference, row_num, [column_num], [area_num])
B28: Returns a reference to specified cells
B30: Array Form Example
B32: Data | C32: Data | G32: Formula | H32: Result | I32: Remarks
B33: Apples | C33: Lemons | D33: =INDEX(B33:C34,2,2) -> Pears | G33: =_xlfn.FORMULATEXT(H33) -> =INDEX(B33:C34,2,2) | H33: =INDEX(B33:C34,2,2) -> Pears | I33: INDEX function in Array format.
B34: Bananas | C34: Pears | D34: {=INDEX(B33:C34,0,1)} -> Apples | G34: =_xlfn.FORMULATEXT(H34) -> {=INDEX(B33:C34,0,1)} | H34: {=INDEX(B33:C34,0,1)} -> Apples | I34: INDEX function in Array format and entered as Array formula. Returns the entire 1st column of the range.
D35: Bananas | G35: =_xlfn.FORMULATEXT(H35) -> {=INDEX(B33:C34,0,1)} | H35: Bananas | I35: INDEX function in Array format and entered as Array formula. Returns the entire 1st column of the range.
B39: Fruit 1 | C39: Price | D39: Count | G39: Formula | H39: Result | I39: Remarks
B40: Apples | C40: 0.69 | D40: 40 | G40: =_xlfn.FORMULATEXT(H40) -> =INDEX(B40:D44,3,3) | H40: =INDEX(B40:D44,3,3) -> 15 | I40: The intersection of the 3rd row and 3rd column in the range B64: D68. Returns the cell reference D66. D66 has value 15, so the formula returns 15
B41: Bananas | C41: 0.34 | D41: 38 | G41: =_xlfn.FORMULATEXT(H41) -> =INDEX((B40:D44,B47:D50),3,2,2) | H41: =INDEX((B40:D44,B47:D50),3,2,2) -> 1.25 | I41: The intersection of the 3rd row and 2nd column in the range B71: D74 as area_num is 2. Returns the cell reference C73. C73 has value 1.25. So the formula returns 1.25 value.
B42: Lemons | C42: 0.55 | D42: 15 | G42: =_xlfn.FORMULATEXT(H42) -> =SUM(D40:INDEX(B40:D44,5,3)) | H42: =SUM(D40:INDEX(B40:D44,5,3)) -> 158 | I42: INDEX part of this formula returns cell reference D68. SUM function returns the sum of range D64: D68.
B43: Oranges | C43: 0.25 | D43: 25
B44: Pears | C44: 0.59 | D44: 40
G45: =INDEX(B40:D44,3,3) -> 15
B46: Fruit 2 | C46: Price | D46: Count | G46: =INDEX((B40:D44,B47:D50),3,2,2) -> 1.25
B47: Almonds | C47: 2.8 | D47: 10 | G47: =SUM(D40:INDEX(B40:D44,5,3)) -> 158
B48: Cashews | C48: 3.55 | D48: 16
B49: Peanuts | C49: 1.25 | D49: 20
B50: Walnuts | C50: 1.75 | D50: 12
B53: INDIRECT(ref_text, [a1])
B54: Returns the reference specified by a text string
B56: Data | C56: Values | G56: Formula | H56: Result | I56: Remarks
B57: C57 | C57: Marissa | D57: =INDIRECT(B57) -> Marissa | G57: =_xlfn.FORMULATEXT(H57) -> =@INDIRECT(B57) | H57: =INDIRECT(B57) -> Marissa | I57: In cell B89, there is a cell reference C89. C89 holds data Marissa. So the formula returns Marissa.
B58: C58 | C58: Kawser | D58: =INDIRECT(B58) -> Kawser | G58: =_xlfn.FORMULATEXT(H58) -> =@INDIRECT("C90") | H58: =INDIRECT("C90") -> 0 | I58: INDIRECT function is directly referring to cell C90.
B59: C59 | C59: Excel | D59: =INDIRECT(B59) -> Excel | G59: =_xlfn.FORMULATEXT(H59) -> =@INDIRECT(B59) | H59: =INDIRECT(B59) -> Excel | I59: Same as the first formula.
B60: Sales_Data | C60: 90000 | D60: =INDIRECT(B60) -> 90000 | G60: =_xlfn.FORMULATEXT(H60) -> =@INDIRECT(B60) | H60: =INDIRECT(B60) -> 90000 | I60: In cell B93, there is a named range Sales_Data. Sales_Data refers to cell C92. C92 has value 90000. So the formula returns 90000.
B61: C61 | C61: 850 | D61: =INDIRECT(B61) -> 850 | G61: =_xlfn.FORMULATEXT(H61) -> =@INDIRECT("C"&B61) | H61: =INDIRECT("C"&B61) -> 0 | I61: "C"&B93 returns C93 as B93 cell has value 93. C93 cell has value 850. So the formula returns 850.
G62: =_xlfn.FORMULATEXT(H62) -> =SUM(INDIRECT("C92:C93")) | H62: =SUM(INDIRECT("C92:C93")) -> 0 | I62: INDIRECT function is directly referring to cell range C92: C93.
B65: OFFSET(reference- rows, cols, [height], [width])
B66: Returns a reference to a range that is a given number of rows and columns from a given reference
B68: Data | C68: Data | D68: Data | G68: Formula | H68: Result | I68: Remarks
B69: 15 | C69: 25 | D69: 8 | G69: =_xlfn.FORMULATEXT(H69) -> =OFFSET(B72,-2,2,1,1) | H69: =OFFSET(B72,-2,2,1,1) -> 7 | I69: Reference point is cell B104. Then goes 2 cells up and reach cell B102, then go 2 cells right and reach cell D102, the height and width is 1 and 1. So the formula returns 7
B70: 20 | C70: 31 | D70: 7 | G70: =_xlfn.FORMULATEXT(H70) -> =SUM(OFFSET(B74,-3,1,2,2)) | H70: =SUM(OFFSET(B74,-3,1,2,2)) -> 54 | I70: Sum of the cells of the range C103: D104
B71: 25 | C71: 12 | D71: 9 | G71: =_xlfn.FORMULATEXT(H71) -> =SUM(OFFSET(B69,0,0,8,3)) | H71: =SUM(OFFSET(B69,0,0,8,3)) -> 402 | I71: Sum of all the cells in the range B101: D108
B72: 9 | C72: 18 | D72: 15
B73: 11 | C73: 18 | D73: 14 | G73: =OFFSET(B72,-2,2,1,1) -> 7
B74: 18 | C74: 10 | D74: 16 | G74: =SUM(OFFSET(B74,-3,1,2,2)) -> 54
B75: 18 | C75: 20 | D75: 17 | G75: =SUM(OFFSET(B69,0,0,8,3)) -> 402
B76: 15 | C76: 15 | D76: 36

Sheet LOGICAL
B2: AND(logical1, [logical2], [logical3], [logical4], …)
B3: Checks whether all arguments are TRUE, and returns TRUE when all arguments are TRUE
G5: Formula | H5: Result | I5: Remarks
C6: =AND(TRUE,TRUE,TRUE) -> TRUE | G6: =_xlfn.FORMULATEXT(H6) -> =AND(TRUE,TRUE,TRUE) | H6: =AND(TRUE,TRUE,TRUE) -> TRUE | I6: All arguments are TRUE, the formula returns TRUE.
C7: =AND(TRUE,FALSE,TRUE,TRUE,TRUE,TRUE) -> FALSE | G7: =_xlfn.FORMULATEXT(H7) -> =AND(TRUE,FALSE,TRUE,TRUE,TRUE,TRUE) | H7: =AND(TRUE,FALSE,TRUE,TRUE,TRUE,TRUE) -> FALSE | I7: One argument is FALSE, the formula returns FALSE.
C8: =AND(1+2=3,3+4=7) -> TRUE | G8: =_xlfn.FORMULATEXT(H8) -> =AND(1+2=3,3+4=7) | H8: =AND(1+2=3,3+4=7) -> TRUE | I8: All arguments are TRUE, the formula returns TRUE.
B12: OR(logical1, [logical2], [logical3], [logical4], …)
B13: Checks whether any of the arguments is TRUE, and returns TRUE or FALSE. Returns FALSE only when all arguments are FALSE
G15: Formula | H15: Result | I15: Remarks
G16: =_xlfn.FORMULATEXT(H16) -> =OR(TRUE) | H16: =OR(TRUE) -> TRUE | I16: One argument is TRUE
G17: =_xlfn.FORMULATEXT(H17) -> =OR(1+1=1,2+2=5) | H17: =OR(1+1=1,2+2=5) -> FALSE | I17: All arguments evaluate to FALSE
G18: =_xlfn.FORMULATEXT(H18) -> =OR(TRUE,FALSE,TRUE) | H18: =OR(TRUE,FALSE,TRUE) -> TRUE | I18: At least one argument is TRUE
G19: =_xlfn.FORMULATEXT(H19) -> =IF(OR(1+1=1,2+2=5,5+5=10),"Answer if true","Answer if false") | H19: =IF(OR(1+1=1,2+2=5,5+5=10),"Answer if true","Answer if false") -> Answer if true | I19: One of the OR arguments are true.
E21: =OR(TRUE) -> TRUE
E22: =OR(1+1=1,2+2=5) -> FALSE
E23: =OR(TRUE,FALSE,FALSE) -> TRUE
E24: =IF(OR(1+1=1,2+2=5,5+5=10),"Answer if true","Answer if false") -> Answer if true
B27: NOT(logical)
B28: Changes FALSE to TRUE, or TRUE to FALSE
G30: Formula | H30: Result | I30: Remarks
G31: =_xlfn.FORMULATEXT(H31) -> =NOT(FALSE) | H31: =NOT(FALSE) -> TRUE | I31: Reverses FALSE
G32: =_xlfn.FORMULATEXT(H32) -> =NOT(TRUE) | H32: =NOT(TRUE) -> FALSE | I32: Reverses TRUE
G33: =_xlfn.FORMULATEXT(H33) -> =NOT(1+1=5) | H33: =NOT(1+1=5) -> TRUE | I33: Reverses FALSE
B35: XOR(logical1, [logical2], [logical3], …)
B36: Returns a logical 'Exclusive Or' of all arguments
G38: Formula | H38: Result | I38: Remarks
G39: =_xlfn.FORMULATEXT(H39) -> =XOR(3>0,2<9) | H39: =_xlfn.XOR(3>0,2<9) -> FALSE | I39: Because one of the two tests evaluates to True, TRUE is returned.
G40: =_xlfn.FORMULATEXT(H40) -> #N/A | I40: Because all test results evaluate to False, FALSE is returned. At least one of the test results must evaluate to True to return TRUE.
G42: =_xlfn.XOR(3>0,2<9) -> FALSE
G43: =_xlfn.XOR(3>12,4>6) -> FALSE

Sheet MISC.
B2: AREAS(reference)
B3: Returns the number of areas in a reference. An area is range of contiguous cells or a single cell
G5: Formula | H5: Result | I5: Remarks
C6: =AREAS(B2:D4) -> 1 | G6: =AREAS(B2:D4) | H6: 1 | I6: Number of areas in the range
C7: =AREAS((B2:D4,E5,F6:I9)) -> 3 | G7: =AREAS((B2:D4,E5,F6:I9)) | H7: 3 | I7: Number of areas in the range
B8: =AREAS(B2:D4 B2) -> 1 | G8: =AREAS(B2:D4 B2) | H8: 1 | I8: Number of areas in the range
B11: CHAR(number)
B12: Returns the character specified by the code number from the character set for your computer
G14: Formula | H14: Result | I14: Remarks
D15: =CHAR(65) -> A | G15: =CHAR(65) | H15: A | I15: Displays the character represented by 65 in the computer's character set.
D16: =CHAR(33) -> ! | G16: =CHAR(33) | H16: ! | I16: Displays the character represented by 33 in the computer's character set.
D17: =CHAR(7) -> _x0007_
B20: CODE(text)
B21: Returns a numeric code for the first character in a text string, in the character set used by your computer
G23: Formula | H23: Result | I23: Remarks
D24: =CODE("A") -> 65 | G24: =CODE("A") | H24: 65 | I24: Returns the numeric code of character A.
D25: =CODE("MARISSA") -> 77 | G25: =CODE("Marissa") | H25: 77 | I25: Returns the numeric code of the first character M of Marissa text.
D26: =CODE("!") -> 33 | G26: =CODE("!") | H26: 33 | I26: Returns the numeric code of character !
D27: =CODE("?") -> 63 | G27: =CODE("?") | H27: 63 | I27: Returns the numeric code of character ?
B30: CLEAN(text)
B31: Removes all non-printable characters from text
B32: Examples of Non-Printable Characters are: Tab, New Line characters. Their codes are 9 and 10
B34: Data | G34: Formula | H34: Result | I34: Remarks
B35: Sales Data | D35: =CLEAN(B35) -> Sales Data | G35: =CLEAN(B32) | H35: Sales Data | I35: This formula cleans up the TAB and NEW LINE non-printable characters from the text.
B39: TRIM(text)
B40: Removes all spaces from a text string except for single spaces between words
B42: Data | G42: Formula | H42: Result | I42: Remarks
B43: Excel Dashboard | D43: =TRIM(B43) -> Excel Dashboard | G43: =TRIM(B40) | H43: Excel Dashboard | I43: Removes all the spaces except for single spaces between words
B44: Titas Gas | D44: =TRIM(B44) -> Titas Gas | G44: =TRIM(" Titas Gas ") | H44: Titas Gas | I44: Removes all the spaces except for single spaces between words
B48: LEN(text)
B49: Returns the number of characters in a text string
B51: Data | G51: Formula | H51: Result | I51: Remarks
B52: Microsoft Excel | D52: =LEN(B52) -> 15 | G52: =LEN(B50) | H52: 15 | I52: Total 15 characters in the cell B30
D53: =LEN(B53) -> 0 | G53: =LEN(B51) | H53: 0 | I53: No characters in the cell B31
D54: =LEN(B54) -> 4 | G54: =LEN(B52) | H54: 4 | I54: 4 Space characters in the cell B32
B55: One | D55: =LEN(B55) -> 3 | G55: =LEN(B54) | H55: 10 | I55: Before Marissa there are 3 space characters.
B56: Marissa | D56: =LEN(B56) -> 10
B60: COLUMN([reference])
B61: Returns the column number of a reference
B62: ROW([reference])
B63: Returns the row number of a reference
G65: Formula | H65: Result | I65: Remarks
C66: =COLUMN() -> 3 | G66: =COLUMN() | H66: 8 | I66: When no reference is used, COLUMN function returns the column number in which the formula appears.
C67: =COLUMN(B30) -> 2 | G67: =COLUMN(B30) | H67: 2 | I67: For reference B30, column number is 2.
C68: =ROW() -> 68 | G68: =ROW() | H68: 66 | I68: When no reference is used, ROW function returns the row number in which the formula appears.
B69: =ROW(B30) -> 30 | G69: =ROW(B30) | H69: 30 | I69: For reference B30, row number is 30.
B73: EXACT(text1, text2)
B74: Checks whether two text strings are exactly the same, and returns TRUE or FALSE. EXACT is case-sensitive
B76: First String | C76: Second String | G76: Formula | H76: Result | I76: Remarks
B77: Excel | C77: excel | E77: =EXACT(B77,C77) -> FALSE | G77: =EXACT(B73,C73) | H77: FALSE | I77: Not exactly same.
B78: Excel | C78: eXcel | E78: =EXACT(B78,C78) -> FALSE | G78: =EXACT(B74,C74) | H78: FALSE | I78: Not exactly same.
B79: Excel | C79: Excel | E79: =EXACT(B79,C79) -> FALSE | G79: =EXACT(B75,C75) | H79: FALSE | I79: Looks exactly same. But second string has a space character in it.
B80: Excel | C80: Excel | E80: =EXACT(B80,C80) -> TRUE | G80: =EXACT(B76,C76) | H80: TRUE | I80: They are exactly same.
B84: FORMULATEXT(reference)
B85: Returns a formula as a string
B87: Formulas | G87: Formula | H87: Result | I87: Remarks
B88: =SUM(5,10,15,50) -> 80 | D88: =_xlfn.FORMULATEXT(B88) -> =SUM(5,10,15,50) | G88: =FORMULATEXT(B84) | H88: =SUM(5,10,15,50) | I88: The formula returns the formula in cell B74 as a text string
B89: =NOW() -> 46312.447 | D89: =_xlfn.FORMULATEXT(B89) -> =NOW() | G89: =FORMULATEXT(B85) | H89: =NOW() | I89: The formula returns the formula in cell B75 as a text string
B90: =TODAY() -> 46312 | D90: =_xlfn.FORMULATEXT(B90) -> =TODAY() | G90: =FORMULATEXT(B86) | H90: =TODAY() | I90: The formula returns the formula in cell B76 as a text string
B94: LEFT(text, [num_chars])
B95: Returns the specified number of characters from the start of a text string
B96: MID(text, start_num, num_chars)
B97: Returns the characters from the middle of a text string, given a starting position and length
B98: RIGHT(text, [num_chars])
B99: Returns the specified number of characters from the end of a text string
B102: Data | G102: Formula | H102: Results | I102: Remarks
B103: Excel Dashboard | D103: =LEFT(B103,5) -> Excel | G103: =LEFT(B116,5) | H103: Excel | I103: Shows the first 5 characters from the cell B106.
B104: Marissa Kawser | D104: =LEFT(B103,30) -> Excel Dashboard | G104: =LEFT(B116,30) | H104: Excel Dashboard | I104: Shows all the characters from the cell B106.
B105: Excel BI Tools | D105: =MID(B103,7,25) -> Dashboard | G105: =MID(B116,7,25) | H105: Dashboard | I105: Shows only the Dashboard part of cell B106.
D106: =MID(B103,50,5) | G106: =MID(B116,50,5) | I106: Shows nothing as start_num 50 is not for the cell B106.
D107: =RIGHT(B103,25) -> Excel Dashboard | G107: =RIGHT(B116,25) | H107: Excel Dashboard | I107: Shows all the characters from the cell B106.
D108: =RIGHT(B105,5) -> Tools | G108: =RIGHT(B118,5) | H108: Tools | I108: Shows the Tools part from the string in the cell B108.
B112: LOWER(text)
B113: Converts all letters in a text string to lowercase
B114: PROPER(text)
B115: Converts a text string to proper case; the first letter in each word in uppercase, and all other letters to lowercase
B116: UPPER(text)
B117: Converts a text string to all uppercase letters
B119: Data | G119: Formula | H119: Result | I119: Remarks
B120: Excel Dashboard | D120: =LOWER(B120) -> excel dashboard | G120: =LOWER(B152) | H120: excel dashboard | I120: Converts all letters to lowercase.
B121: marissa kawser | D121: =PROPER(B121) -> Marissa Kawser | G121: =PROPER(B153) | H121: Marissa Kawser | I121: Converts the text strings to proper case. M and K are now in uppercase.
B122: Excel BI Tools | D122: =UPPER(B122) -> EXCEL BI TOOLS | G122: =UPPER(B154) | H122: EXCEL BI TOOLS | I122: Coverts the text string to all uppercase letters.
B126: REPT(text, number_times)
B127: Repeats text a given number of times. Use REPT to fill a cell with a number of instances of a text string
G129: Formula | H129: Result | I129: Remarks
C130: =REPT("*-",3) -> *-*-*- | G130: =REPT("*-",3) | H130: *-*-*- | I130: Fills the cell with 3 number of instances using *- string.
C131: =REPT("-",10) -> ---------- | G131: =REPT("-",10) | H131: ---------- | I131: Fills the cell with 10 number of instances using - letter.
B134: SHEET([value])
B135: Returns the sheet number of the referenced sheet
B137: The SHEET function syntax has the following arguments.
B138: n Value Optional. Value is the name of a sheet or a reference for which you want the sheet number. If value is omitted, SHEET returns the number of the sheet that contains the function.
B140: Sheet | G140: Formula | H140: Result | I140: Remarks
B141: LIST OF FUNCTIONS | D141: =_xlfn.SHEET("MATHEMATICAL") -> 9 | G141: =SHEET("LIST OF FUNCTIONS") | H141: 2 | I141: Showing the Sheet number of "LIST OF FUNCTIONS" worksheet.
B142: List of Functions | D142: =_xlfn.SHEET() -> 14 | G142: =SHEET() | H142: 10 | I142: Showing the Sheet number of the current worksheet.
B143: RANK | D143: =_xlfn.SHEET(Sales_Data) -> 12 | G143: =SHEET(Sales_Data) | H143: 8 | I143: Showing the Sheet number where the Sales_Data named range available.
D144: =_xlfn.SHEET("DATE & TIME") -> 11 | G144: =SHEET('DATE & TIME'!B157) | H144: 9 | I144: Showing the Sheet number of DATE & TIME worksheet.
B148: SHEETS([reference])
B149: Returns the number of sheets in a reference
B151: The SHEETS function syntax has the following arguments.
B152: n Reference Optional. Reference is a reference for which you want to know the number of sheets it contains. If Reference is omitted, SHEETS returns the number of sheets in the workbook that contains the function.
...

Sheet RANK
B2: RANK(number, ref, [order])
B3: This function is available for compatibility with Excel 2007 and other.
B4: Returns the rank of a number in a list of numbers: its size relative to other values in the list
B6: Data | G6: Formula | H6: Result | I6: Remarks
B7: 7 | D7: =RANK(B8,B7:B11) -> 2 | G7: =RANK(B8,B7:B11) | H7: 2 | I7: Order is 0 or omitted, the values are arranged in descending order.
B8: 3.5 | D8: =RANK(B9,B7:B11) -> 2 | G8: =RANK(B9,B7:B11) | H8: 2 | I8: RANK function gives duplicate numbers same rank.
B9: 3.5 | D9: =RANK(B10,B7:B11,1) -> 1 | G9: =RANK(B10,B7:B11,1) | H9: 1 | I9: Order is 1, the values are arranged in ascending order.
B10: 1 | D10: =RANK(B10,B7:B11,0) -> 5 | G10: =RANK(B10,B7:B11,0) | H10: 5 | I10: Order is 0 or omitted, the values are arranged in descending order.
B11: 2
B14: RANK.AVG(number, ref, [order])
B15: Returns the rank of a number in a list of numbers: its size relative to other values in the list; if more than one value has the same rank, the average rank is returned
B17: Data | G17: Formula | H17: Result | I17: Remarks
B18: 89 | D18: =_xlfn.RANK.AVG(B19,B18:B25) -> 4 | G18: =RANK.AVG(B28,B27:B34) | H18: 4 | I18: Numbers are arranged in descending order and 90 ranks 4.
B19: 90 | D19: =_xlfn.RANK.AVG(B24,B18:B25,1) -> 1.5 | G19: =RANK.AVG(B33,B27:B34,1) | H19: 1.5 | I19: You get the average rank of number 85 when the numbers are in ascending order.
B20: 87 | D20: =_xlfn.RANK.AVG(B25,B18:B25,1) -> 7.5 | G20: =RANK.AVG(B34,B27:B34,1) | H20: 7.5 | I20: You get the average rank of number 98 when the numbers are in ascending order.
B21: 98
B22: 96
B23: 85
B24: 85
B25: 98
B28: RANK.EQ(number, ref, [order])
B29: Returns the rank of a number in a list of numbers: its size relative to other values in the list; if more than one value has the same rnak, the top rank of that set of values is returned
B31: Data | G31: Formula | H31: Result | I31: Remarks
B32: 89 | D32: =_xlfn.RANK.EQ(B33,B32:B39) -> 4 | G32: =RANK.EQ(B43,B42:B49) | H32: 4 | I32: Numbers are arranged in descending order and 90 ranks 4.
B33: 90 | D33: =_xlfn.RANK.EQ(B38,B32:B39,1) -> 1 | G33: =RANK.EQ(B48,B42:B49,1) | H33: 1 | I33: You get the top rank of number 85 when the numbers are in ascending order.
B34: 87 | D34: =_xlfn.RANK.EQ(B39,B32:B39,1) -> 7 | G34: =RANK.EQ(B49,B42:B49,1) | H34: 7 | I34: You get the top rank of number 98 when the numbers are in ascending order.
B35: 98 | H35: 7 | I35: You get the top rank of number 98 when the numbers are in ascending order.
B36: 96
B37: 85
B38: 85
B39: 98

Sheet CONDITIONAL
B2: =AVERAGEIF(range, criteria, [average_range])
B3: Finds average (arithmetic mean) for the cells specified by a given condition or criteria
B5: Region | C5: Sales | F5: Formula | G5: Result | H5: Remarks
B6: East | C6: 500 | F6: =AVERAGEIF(B6:B27,"East",C6:C27) | G6: 267.5 | H6: Average of all the Sales for East region.
B7: West | C7: 50 | F7: =AVERAGEIF(B6:B27,"North",C6:C27) | G7: 62.5 | H7: Average of all the Sales for North region.
B8: North | C8: 100 | F8: =AVERAGEIF(B6:B27,"North*",C6:C27) | G8: 55 | H8: Average of all the Sales for North region (including North (New Office) region).
B9: South | C9: 25 | F9: =AVERAGEIF(B6:B27,"*New Office",C6:C27) | G9: 35 | H9: Average of all the Sales for the New Offices.
B10: Mid West | C10: 200 | F10: =AVERAGEIF(B6:B27,">=4",C6:C27) | G10: 58.75 | H10: Average of all the Sales for the values greater than or equal to 4.
B11: South New Office | C11: 30 | F11: =AVERAGEIF(B6:B27,5,C6:C27) | G11: 75 | H11: Average of all the Sales for the values equal to 5.
B12: East | C12: 35 | F12: =AVERAGEIF(B6:B27,TRUE,C6:C27) | G12: 110 | H12: Average of all the Sales for the values equal to TRUE statement.
B13: West | C13: 50 | F13: =AVERAGEIF(B6:B27,FALSE,C6:C27) | G13: 77.5 | H13: Average of all the Sales for the values equal to FALSE statement.
B14: South | C14: 15
B15: North | C15: 25 | F15: =AVERAGEIF(B6:B27,"East",C6:C27) -> 267.5
B16: North New Office | C16: 40 | F16: =AVERAGEIF(B6:B27,"North",C6:C27) -> 62.5
B17: 5 | C17: 50 | F17: =AVERAGEIF(B6:B27,"North*",C6:C27) -> 55
B18: 5 | C18: 100 | F18: =AVERAGEIF(B6:B27,"*New Office",C6:C27) -> 35
B19: 2 | C19: 200 | F19: =AVERAGEIF(B6:B27,">=4",C6:C27) -> 58.75
B20: 4 | C20: 35 | F20: =AVERAGEIF(B6:B27,5,C6:C27) -> 75
B21: 2 | C21: 45 | F21: =AVERAGEIF(B6:B27,TRUE,C6:C27) -> 110
B22: 4 | C22: 50 | F22: =AVERAGEIF(B6:B27,FALSE,C6:C27) -> 77.5
B23: TRUE | C23: 90
B24: FALSE | C24: 100
B25: TRUE | C25: 125
B26: TRUE | C26: 115
B27: FALSE | C27: 55
D30: SUMIF(range, criteria, [sum_range])
B31: Adds the cells specified by a given condition or criteria
B33: Region | C33: Sales | F33: Formula | G33: Result | H33: Remarks
B34: East | C34: 500 | F34: =SUMIF(B36:B57,"East",C36:C57) | G34: 535 | H34: Sum of all the Sales for East region.
B35: West | C35: 50 | F35: =SUMIF(B36:B57,"North",C36:C57) | G35: 125 | H35: Sum of all the Sales for North region.
B36: North | C36: 100 | F36: =SUMIF(B36:B57,"North*",C36:C57) | G36: 165 | H36: Sum of all the Sales for North region (including North (New Office) region).
B37: South | C37: 25 | F37: =SUMIF(B36:B57,"*New Office",C36:C57) | G37: 70 | H37: Sum of all the Sales for the New Offices.
B38: Mid West | C38: 200 | F38: =SUMIF(B36:B57,">=4",C36:C57) | G38: 235 | H38: Sum of all the Sales for the values greater than or equal to 4.
B39: South New Office | C39: 30 | F39: =SUMIF(B36:B57,5,C36:C57) | G39: 150 | H39: Sum of all the Sales for the values equal to 5.
B40: East | C40: 35 | F40: =SUMIF(B36:B57,TRUE,C36:C57) | G40: 330 | H40: Sum of all the Sales for the values equal to TRUE statement.
B41: West | C41: 50 | F41: =SUMIF(B36:B57,FALSE,C36:C57) | G41: 155 | H41: Sum of all the Sales for the values equal to FALSE statement.
B42: South | C42: 15
B43: North | C43: 25 | F43: =SUMIF(B36:B57,"East",C36:C57) -> 35
B44: North New Office | C44: 40 | F44: =SUMIF(B36:B57,"North",C36:C57) -> 125
B45: 5 | C45: 50 | F45: =SUMIF(B36:B57,"North*",C36:C57) -> 165
B46: 5 | C46: 100 | F46: =SUMIF(B36:B57,"*New Office",C36:C57) -> 70
B47: 2 | C47: 200 | F47: =SUMIF(B36:B57,">=4",C36:C57) -> 235
B48: 4 | C48: 35 | F48: =SUMIF(B36:B57,5,C36:C57) -> 150
B49: 2 | C49: 45 | F49: =SUMIF(B36:B57,TRUE,C36:C57) -> 330
B50: 4 | C50: 50 | F50: =SUMIF(B36:B57,FALSE,C36:C57) -> 155
B51: TRUE | C51: 90
B52: FALSE | C52: 100
B53: TRUE | C53: 125
B54: TRUE | C54: 115
B55: FALSE | C55: 55
B58: COUNTIF(range, criteria)
B59: Counts the number of cells within a range that meet the given condition
B61: Region | C61: Sales | F61: Formula | G61: Result | H61: Remarks
B62: East | C62: 500 | F62: =COUNTIF(B66:B87,"East") | G62: 2 | H62: Count the number of cells with East in cells B66 through B87.
B63: West | C63: 50 | F63: =COUNTIF(B66:B87,"North") | G63: 2 | H63: Count the number of cells with North in cells B66 through B87.
B64: North | C64: 100 | F64: =COUNTIF(C66:C87,">=100") | G64: 8 | H64: Count the number of cells with values greater than and equal to 100.
B65: South | C65: 25 | F65: =COUNTIF(C66:C87,"<="&C6) -> 18 | G65: 17 | H65: Count the number of cells with values less than and equal to the value of cell C68.
B66: Mid West | C66: 200 | F66: =COUNTIF(B66:B87,"No*") | G66: 3 | H66: Count the number of cells with values that start with "No" characters.
B67: South New Office | C67: 30 | F67: =COUNTIF(B66:B87,"Ea??") | G67: 2 | H67: Count the number of cells with values that start with "Ea" characters and then have any two characters.
B68: East | C68: 35
B69: West | C69: 50 | F69: =COUNTIF(B62:B83,"East") -> 2
B70: South | C70: 15 | F70: =COUNTIF(B62:B83,"North") -> 2
B71: North | C71: 25 | F71: =COUNTIF(C62:C83,">=100") -> 8
B72: North New Office | C72: 40 | F72: =COUNTIF(C62:C83,"<="&C64) -> 17
B73: 5 | C73: 50 | F73: =COUNTIF(B62:B83,"No*") -> 3
B74: 5 | C74: 100 | F74: =COUNTIF(B62:B83,"Ea??") -> 2
B75: 2 | C75: 200
B76: 4 | C76: 35
B77: 2 | C77: 45
B78: 4 | C78: 50
B79: TRUE | C79: 90
B80: FALSE | C80: 100
B81: TRUE | C81: 125
B82: TRUE | C82: 115
B83: FALSE | C83: 55
B86: AVERAGEIFS(average_range, criteria_range1, criteria1, [criteria_range2, criteria2], [criteria_range3, criteria3], …)
B87: Finds average (arithmetic mean) for the cells specified by a given set of conditions or criteria
B89: Product | C89: Sales Person | D89: Quantity Sold | F89: Formula | G89: Result | H89: Remarks
B90: Apple | C90: Tom | D90: 10 | F90: =AVERAGEIFS(D96:D108,B96:B108,"Apple",C96:C108,"Tom") | G90: 13.333333 | H90: Average Quantity Sold of Apple product by Sales Person Tom.
B91: Orange | C91: Jon | D91: 4 | F91: =AVERAGEIFS(D96:D108,B96:B108,"Banana",C96:C108,"Marissa") | G91: #DIV/0! | H91: Average Quantity Sold of Banana product by Sales Person Marissa. Marissa didn't sell Banana. So #DIV/0! error is showing in the cell.
B92: Apple | C92: Marissa | D92: 12 | F92: =AVERAGEIFS(D96:D108,B96:B108,"Carrot",C96:C108,"Marissa") | G92: 17 | H92: Average Quantity Sold of Carrot product by Sales Person Marissa.
B93: Carrot | C93: Kawser | D93: 5
B94: Banana | C94: Khan | D94: 13 | F94: =AVERAGEIFS(D90:D102,B90:B102,"Apple",C90:C102,"Tom") -> 13.333333
B95: Apple | C95: Tom | D95: 15 | F95: =AVERAGEIFS(D90:D102,B90:B102,"Banana",C90:C102,"Marissa") -> #DIV/0!
B96: Banana | C96: Jon | D96: 14 | F96: =AVERAGEIFS(D90:D102,B90:B102,"Carrot",C90:C102,"Marissa") -> 17
B97: Carrot | C97: Kawser | D97: 12
B98: Orange | C98: Jon | D98: 8
B99: Carrot | C99: Marissa | D99: 9
B100: Apple | C100: Tom | D100: 15
B101: Banana | C101: Jon | D101: 20
B102: Carrot | C102: Marissa | D102: 25
B105: SUMIFS(sum_range, criteria_range1, criteria1, [criteria_range2, criteria2], [criteria_range3, criteria3], …)
B106: Adds the cells specified by a given set of conditions or criteria
B108: Product | C108: Sales Person | D108: Quantity Sold | F108: Formula | G108: Result | H108: Remarks
B109: Apple | C109: Tom | D109: 10 | F109: =SUMIFS(D119:D131,B119:B131,"Apple",C119:C131,"Tom") | G109: 40 | H109: Sums the Quantity Sold of Apple product by Sales Person Tom.
B110: Orange | C110: Jon | D110: 4 | F110: =SUMIFS(D119:D131,B119:B131,"Banana",C119:C131,"Marissa") | G110: 0 | H110: Sums the Quantity Sold of Banana product by Sales Person Marissa. Marissa didn't sell Banana. So #DIV/0! error is showing in the cell.
B111: Apple | C111: Marissa | D111: 12 | F111: =SUMIFS(D119:D131,B119:B131,"Carrot",C119:C131,"Marissa") | G111: 34 | H111: Sums the Quantity Sold of Carrot product by Sales Person Marissa.
B112: Carrot | C112: Kawser | D112: 5
B113: Banana | C113: Khan | D113: 13 | F113: =SUMIFS(D109:D121,B109:B121,"Apple",C109:C121,"Tom") -> 40
B114: Apple | C114: Tom | D114: 15 | F114: =SUMIFS(D109:D121,B109:B121,"Banana",C109:C121,"Marissa") -> 0
...

Sheet LOOKUP
B2: MATCH(lookup_value, lookup_array, [match_type])
B3: Returns the relative position of an item in an array that matches a specified value in a specified order
B5: Product | C5: Count1 (Ascending) | D5: Count2 (Descending) | E5: Count3 (No Order)
B6: Apple | C6: 35 | D6: 45 | E6: 25 | G6: =MATCH(41,C6:C9,1) -> 3
B7: Orange | C7: 38 | D7: 40 | E7: 30 | G7: =MATCH(41,C6:C9,0) -> #N/A
B8: Banana | C8: 40 | D8: 38 | E8: 28 | G8: =MATCH(41,C6:C9,-1) -> #N/A
B9: Pears | C9: 45 | D9: 35 | E9: 15 | G9: =MATCH(41,D6:D9,-1) -> 1
G10: =MATCH(28,E6:E9,0) -> 3
B13: LOOKUP(lookup_value, lookup_vector, [result_vector])
B14: Looks up a value either from a one-row or one-column range or from an array. Provided for backward compatibility
B16: Part Number | C16: Serial | D16: Part Price | E16: Status
B17: A001 | C17: 10 | D17: 200 | E17: In Stock | F17: =LOOKUP("A003",B17:B22,D17:D22) -> 300
B18: A002 | C18: 20 | D18: 500 | E18: In Stock | F18: =LOOKUP(20,C17:C22,D17:D22) -> 500
B19: A003 | C19: 30 | D19: 300 | E19: In Stock | F19: =LOOKUP(25,C17:C22,D17:D22) -> 500
B20: A004 | C20: 40 | D20: 150 | E20: In Stock | F20: =LOOKUP(5,C17:C22,D17:D22) -> #N/A
B21: A005 | C21: 50 | D21: 225
B22: A006 | C22: 60 | D22: 525
B25: HLOOKUP(lookup_value, table_array, row_index_num, [range_lookup])
B26: Looks for a value in the top row of a table or array of values and return the value in the same column from a row you specify
B28: Month | C28: Axles | D28: Bearings | E28: Bolts
B29: Jan | C29: 4 | D29: 7 | E29: 9 | F29: =HLOOKUP("Axles",B28:E31,2,TRUE) -> 4
B30: Feb | C30: 5 | D30: 8 | E30: 10 | F30: =HLOOKUP("Bearings",C28:E31,3,FALSE) -> 8
B31: Mar | C31: 6 | D31: 9 | E31: 11 | F31: =HLOOKUP("B",B28:E31,3,TRUE) -> 5
B34: VLOOKUP(lookup_value, table_array, col_index_num, [range_lookup])
B35: Looks for a value in the leftmost column in a table, then returns a value in the same row from a column you specify. By default, the table must be sorted in an ascending order
B37: ID | C37: first name | D37: last name | E37: title | F37: Birth date | H37: Formula | I37: Result | J37: Remarks
B38: ID | C38: Davis | D38: Sara | E38: Sales Rep. | F38: 25062 | H38: =_xlfn.FORMULATEXT(I38) -> =VLOOKUP("Leal",C38:F43,3,FALSE) | I38: =VLOOKUP("Leal",C38:F43,3,FALSE) -> Sales Rep. | J38: In the range C59: F64, the formula looks up "Leal" in the first column, when found it shows the Title of Leal at 3rd column in the same row. FALSE returns an exact match.
B39: 105 | C39: Fontana | D39: Olivier | E39: V.P. of Sales | F39: 19043 | H39: =_xlfn.FORMULATEXT(I39) -> =VLOOKUP(111,B38:F43,5,FALSE) | I39: =VLOOKUP(111,B38:F43,5,FALSE) -> 21447 | J39: In the range B59: F64, the formula looks up value 111 in the frist column, when found it shows the Birth Date at 5th column in the same row. FALSE returns an exact match.
B40: 108 | C40: Leal | D40: Karina | E40: Sales Rep. | F40: 23253 | H40: =_xlfn.FORMULATEXT(I40) -> =VLOOKUP(110,B38:F43,4,FALSE) | I40: =VLOOKUP(110,B38:F43,4,FALSE) -> #N/A | J40: There is no ID as 110 in the first column of range B59: F64 and the VLOOKUP function will return an exact match. So the function returns #N/A.
B41: 111 | C41: Patten | D41: Michael | E41: Manager | F41: 21447 | H41: =_xlfn.FORMULATEXT(I41) -> =VLOOKUP(114,B38:F43,4,TRUE) | I41: =VLOOKUP(114,B38:F43,4,TRUE) -> Manager | J41: There is no ID as 114 in the first column of range B59: F64, but the VLOOKUP function will return an appropriate match, VLOOKUP function returns the Title of ID 111. 111 is the nearest value of 114 and less than 114.
B42: 115 | C42: Burke | D42: Brian | E42: Sales Mgr. | F42: 20182
B43: 120 | C43: Sousa | D43: Luis | E43: Sales Rep. | F43: 23049
B45: =VLOOKUP("Leal",C38:F43,3,FALSE) -> Sales Rep.
B46: =VLOOKUP(111,B38:F43,5,FALSE) -> 21447
B47: =VLOOKUP(110,B38:F43,4,FALSE) -> #N/A
B48: =VLOOKUP(114,B38:F43,4,TRUE) -> Manager

Sheet IF QS
A1: TOPIC 1: IF FUNCTION
A3: Dataset: Student Exam Results — Greenwood High School, Class X, Mathematics
A4: S.No | B4: Student Name | C4: Subject | D4: Marks (out of 100) | E4: Result (Q1) | F4: Grade (Q2) | G4: MERIT/NO MERIT | H4: RE EXAM/CLEARED | I4: PERFOMANCE | J4: % | K4: TOPPER
A5: 1 | B5: Aarav Sharma | C5: Mathematics | D5: 92 | E5: =IF(D5>=40,"PASS","FAIL") -> PASS | F5: =IF(D5>=90,"A+",IF(D5>=75,"A",IF(D5>=60,"B",IF(D5>=40,"C",IF(D5<40,"F"))))) -> A+ | G5: =IF(D5>=85,"MERIT","NO MERIT") -> MERIT | H5: =IF(D5<40,"RE - EXAM","CLEARED") -> CLEARED | I5: =IF(D5>=90,"EXCELLENT",IF(D5>=70,"GOOD",IF(D5>=40,"AVERAGE",IF(D5<40,"NEED IMPROVEMENT")))) -> EXCELLENT | J5: =D5/100 -> 0.92 | K5: =IF(D5=MAX($D$5:$D$16),"TOPPER","-") -> -
A6: 2 | B6: Priya Nair | C6: Mathematics | D6: 38 | E6: =IF(D6>=40,"PASS","FAIL") -> FAIL | F6: =IF(D6>=90,"A+",IF(D6>=75,"A",IF(D6>=60,"B",IF(D6>=40,"C",IF(D6<40,"F"))))) -> F | G6: =IF(D6>=85,"MERIT","NO MERIT") -> NO MERIT | H6: =IF(D6<40,"RE - EXAM","CLEARED") -> RE - EXAM | I6: =IF(D6>=90,"EXCELLENT",IF(D6>=70,"GOOD",IF(D6>=40,"AVERAGE",IF(D6<40,"NEED IMPROVEMENT")))) -> NEED IMPROVEMENT | J6: =D6/100 -> 0.38 | K6: =IF(D6=MAX($D$5:$D$16),"TOPPER","-") -> -
A7: 3 | B7: Rohan Mehta | C7: Mathematics | D7: 67 | E7: =IF(D7>=40,"PASS","FAIL") -> PASS | F7: =IF(D7>=90,"A+",IF(D7>=75,"A",IF(D7>=60,"B",IF(D7>=40,"C",IF(D7<40,"F"))))) -> B | G7: =IF(D7>=85,"MERIT","NO MERIT") -> NO MERIT | H7: =IF(D7<40,"RE - EXAM","CLEARED") -> CLEARED | I7: =IF(D7>=90,"EXCELLENT",IF(D7>=70,"GOOD",IF(D7>=40,"AVERAGE",IF(D7<40,"NEED IMPROVEMENT")))) -> AVERAGE | J7: =D7/100 -> 0.67 | K7: =IF(D7=MAX($D$5:$D$16),"TOPPER","-") -> -
A8: 4 | B8: Sneha Iyer | C8: Mathematics | D8: 45 | E8: =IF(D8>=40,"PASS","FAIL") -> PASS | F8: =IF(D8>=90,"A+",IF(D8>=75,"A",IF(D8>=60,"B",IF(D8>=40,"C",IF(D8<40,"F"))))) -> C | G8: =IF(D8>=85,"MERIT","NO MERIT") -> NO MERIT | H8: =IF(D8<40,"RE - EXAM","CLEARED") -> CLEARED | I8: =IF(D8>=90,"EXCELLENT",IF(D8>=70,"GOOD",IF(D8>=40,"AVERAGE",IF(D8<40,"NEED IMPROVEMENT")))) -> AVERAGE | J8: =D8/100 -> 0.45 | K8: =IF(D8=MAX($D$5:$D$16),"TOPPER","-") -> -
A9: 5 | B9: Kabir Singh | C9: Mathematics | D9: 81 | E9: =IF(D9>=40,"PASS","FAIL") -> PASS | F9: =IF(D9>=90,"A+",IF(D9>=75,"A",IF(D9>=60,"B",IF(D9>=40,"C",IF(D9<40,"F"))))) -> A | G9: =IF(D9>=85,"MERIT","NO MERIT") -> NO MERIT | H9: =IF(D9<40,"RE - EXAM","CLEARED") -> CLEARED | I9: =IF(D9>=90,"EXCELLENT",IF(D9>=70,"GOOD",IF(D9>=40,"AVERAGE",IF(D9<40,"NEED IMPROVEMENT")))) -> GOOD | J9: =D9/100 -> 0.81 | K9: =IF(D9=MAX($D$5:$D$16),"TOPPER","-") -> -
A10: 6 | B10: Ananya Das | C10: Mathematics | D10: 29 | E10: =IF(D10>=40,"PASS","FAIL") -> FAIL | F10: =IF(D10>=90,"A+",IF(D10>=75,"A",IF(D10>=60,"B",IF(D10>=40,"C",IF(D10<40,"F"))))) -> F | G10: =IF(D10>=85,"MERIT","NO MERIT") -> NO MERIT | H10: =IF(D10<40,"RE - EXAM","CLEARED") -> RE - EXAM | I10: =IF(D10>=90,"EXCELLENT",IF(D10>=70,"GOOD",IF(D10>=40,"AVERAGE",IF(D10<40,"NEED IMPROVEMENT")))) -> NEED IMPROVEMENT | J10: =IFERROR(D10/0,"CHECK DATA") -> CHECK DATA | K10: =IF(D10=MAX($D$5:$D$16),"TOPPER","-") -> -
A11: 7 | B11: Vivaan Rao | C11: Mathematics | D11: 58 | E11: =IF(D11>=40,"PASS","FAIL") -> PASS | F11: =IF(D11>=90,"A+",IF(D11>=75,"A",IF(D11>=60,"B",IF(D11>=40,"C",IF(D11<40,"F"))))) -> C | G11: =IF(D11>=85,"MERIT","NO MERIT") -> NO MERIT | H11: =IF(D11<40,"RE - EXAM","CLEARED") -> CLEARED | I11: =IF(D11>=90,"EXCELLENT",IF(D11>=70,"GOOD",IF(D11>=40,"AVERAGE",IF(D11<40,"NEED IMPROVEMENT")))) -> AVERAGE | J11: =D11/100 -> 0.58 | K11: =IF(D11=MAX($D$5:$D$16),"TOPPER","-") -> -
A12: 8 | B12: Ishita Kapoor | C12: Mathematics | D12: 96 | E12: =IF(D12>=40,"PASS","FAIL") -> PASS | F12: =IF(D12>=90,"A+",IF(D12>=75,"A",IF(D12>=60,"B",IF(D12>=40,"C",IF(D12<40,"F"))))) -> A+ | G12: =IF(D12>=85,"MERIT","NO MERIT") -> MERIT | H12: =IF(D12<40,"RE - EXAM","CLEARED") -> CLEARED | I12: =IF(D12>=90,"EXCELLENT",IF(D12>=70,"GOOD",IF(D12>=40,"AVERAGE",IF(D12<40,"NEED IMPROVEMENT")))) -> EXCELLENT | J12: =D12/100 -> 0.96 | K12: =IF(D12=MAX($D$5:$D$16),"TOPPER","-") -> TOPPER
A13: 9 | B13: Aditya Verma | C13: Mathematics | D13: 40 | E13: =IF(D13>=40,"PASS","FAIL") -> PASS | F13: =IF(D13>=90,"A+",IF(D13>=75,"A",IF(D13>=60,"B",IF(D13>=40,"C",IF(D13<40,"F"))))) -> C | G13: =IF(D13>=85,"MERIT","NO MERIT") -> NO MERIT | H13: =IF(D13<40,"RE - EXAM","CLEARED") -> CLEARED | I13: =IF(D13>=90,"EXCELLENT",IF(D13>=70,"GOOD",IF(D13>=40,"AVERAGE",IF(D13<40,"NEED IMPROVEMENT")))) -> AVERAGE | J13: =D13/100 -> 0.4 | K13: =IF(D13=MAX($D$5:$D$16),"TOPPER","-") -> -
A14: 10 | B14: Meera Pillai | C14: Mathematics | D14: 73 | E14: =IF(D14>=40,"PASS","FAIL") -> PASS | F14: =IF(D14>=90,"A+",IF(D14>=75,"A",IF(D14>=60,"B",IF(D14>=40,"C",IF(D14<40,"F"))))) -> B | G14: =IF(D14>=85,"MERIT","NO MERIT") -> NO MERIT | H14: =IF(D14<40,"RE - EXAM","CLEARED") -> CLEARED | I14: =IF(D14>=90,"EXCELLENT",IF(D14>=70,"GOOD",IF(D14>=40,"AVERAGE",IF(D14<40,"NEED IMPROVEMENT")))) -> GOOD | J14: =D14/100 -> 0.73 | K14: =IF(D14=MAX($D$5:$D$16),"TOPPER","-") -> -
A15: 11 | B15: Arjun Bose | C15: Mathematics | D15: 88 | E15: =IF(D15>=40,"PASS","FAIL") -> PASS | F15: =IF(D15>=90,"A+",IF(D15>=75,"A",IF(D15>=60,"B",IF(D15>=40,"C",IF(D15<40,"F"))))) -> A | G15: =IF(D15>=85,"MERIT","NO MERIT") -> MERIT | H15: =IF(D15<40,"RE - EXAM","CLEARED") -> CLEARED | I15: =IF(D15>=90,"EXCELLENT",IF(D15>=70,"GOOD",IF(D15>=40,"AVERAGE",IF(D15<40,"NEED IMPROVEMENT")))) -> GOOD | J15: =D15/100 -> 0.88 | K15: =IF(D15=MAX($D$5:$D$16),"TOPPER","-") -> -
A16: 12 | B16: Diya Menon | C16: Mathematics | D16: 34 | E16: =IF(D16>=40,"PASS","FAIL") -> FAIL | F16: =IF(D16>=90,"A+",IF(D16>=75,"A",IF(D16>=60,"B",IF(D16>=40,"C",IF(D16<40,"F"))))) -> F | G16: =IF(D16>=85,"MERIT","NO MERIT") -> NO MERIT | H16: =IF(D16<40,"RE - EXAM","CLEARED") -> RE - EXAM | I16: =IF(D16>=90,"EXCELLENT",IF(D16>=70,"GOOD",IF(D16>=40,"AVERAGE",IF(D16<40,"NEED IMPROVEMENT")))) -> NEED IMPROVEMENT | J16: =D16/100 -> 0.34 | K16: =IF(D16=MAX($D$5:$D$16),"TOPPER","-") -> -
A18: QUESTIONS
A19: Q1. The school pass mark is 40. In the 'Result' column, write an formula that displays "Pass" if a student's marks are 40 or above, otherwise "Fail".
A20: Q2. In the 'Grade' column, write a NESTED IF formula that assigns grades based on marks: A+ (>=90), A (>=75), B (>=60), C (>=40), F (below 40).
A21: Q3. The principal wants to award a "Merit Certificate" to students who scored between 85 and 100 (inclusive). Write an IF formula using the AND function to display "Merit" or "No Merit".
A22: Q4. Students scoring below 40 OR with a blank marks cell must appear for a re-exam. Write an IF formula using OR that displays "Re-exam" or "Cleared".
A23: Q5. Create a 4-tier performance remark using nested IF: "Excellent" (>=90), "Good" (>=70), "Average" (>=40), "Needs Improvement" (<40).
A24: Q6. Suppose a teacher accidentally divides a student's marks by zero while calculating percentage in another cell, producing a division error. Write a formula using IFERROR that displays "Check Data" instead of the error.
A25: Q7. Write an IF formula that displays "Topper" for the single highest mark in the dataset and "-" for everyone else (Hint: combine IF with MAX).

Sheet MATHS
A1: TOPIC 2: MATHEMATICAL FUNCTIONS
A3: Dataset: Quarterly Sales Report — Sunrise Retail Stores (figures in Rs.)
A4: SalesRep | B4: Region | C4: Jan Sales | D4: Feb Sales | E4: Mar Sales | F4: Emp ID | G4: Total (Q1) | H4: EVEN OR ODD | I4: SQRT | J4: 5% BONUS | K4: NORTH REGION | L4: SOUTH REGION > 45,000 | M4: AVG SALES | N4: AVG MARCH SALES | O4: ROUND | P4: ROUND UP FEB | Q4: ROUND DOWN JAN | R4: MAX | S4: MIN | T4: TOP PERFORMER
A5: Ravi Kumar | B5: North | C5: 45000 | D5: 52000 | E5: 48500 | F5: 101 | G5: =SUM(C5:E5) -> 145500 | H5: {=IF(MOD(F5:F14,2)=0,"EVEN","ODD")} -> ODD | I5: =SQRT(MAX(G5:G14)) -> 460.97722 | J5: {=POWER(G5:G14,1.05^2)} -> 492103.5 | K5: =SUMIF(B5:B14,"North",C5:C14) -> 134000 | L5: =SUMIFS(D5:D14,B5:B14,"SOUTH",C5:C14,">45000") -> 109000 | M5: =AVERAGE(C5:E5) -> 48500 | N5: =AVERAGEIF(B5:B14,"EAST",E5:E14) -> 58750 | O5: {=ROUND(G5:G14,-2)} -> 145500 | P5: {=ROUNDUP(D5:D14,-3)} -> 52000 | Q5: {=ROUNDDOWN(C5:C14,-3)} -> 45000 | R5: =MAX(G5:G14) -> 212500 | S5: =MIN(G5:G14) -> 118500 | T5: =INDEX(A5:A14,MATCH(MAX(G5:G14),G5:G14,0)) -> Farah Khan
A6: Sunita Rao | B6: South | C6: 62000 | D6: 58000 | E6: 61000 | F6: 102 | G6: =SUM(C6:E6) -> 181000 | H6: EVEN | J6: 626023.49 | M6: =AVERAGE(C6:E6) -> 60333.333 | O6: 181000 | P6: 58000 | Q6: 62000
A7: Manoj Tiwari | B7: North | C7: 38000 | D7: 41000 | E7: 39500 | F7: 103 | G7: =SUM(C7:E7) -> 118500 | H7: ODD | J7: 392441.1 | M7: =AVERAGE(C7:E7) -> 39500 | O7: 118500 | P7: 41000 | Q7: 38000
A8: Farah Khan | B8: East | C8: 71000 | D8: 68000 | E8: 73500 | F8: 104 | G8: =SUM(C8:E8) -> 212500 | H8: EVEN | J8: 747159.33 | M8: =AVERAGE(C8:E8) -> 70833.333 | O8: 212500 | P8: 68000 | Q8: 71000
A9: Deepak Joshi | B9: West | C9: 55000 | D9: 49000 | E9: 52500 | F9: 105 | G9: =SUM(C9:E9) -> 156500 | H9: ODD | J9: 533276.03 | M9: =AVERAGE(C9:E9) -> 52166.667 | O9: 156500 | P9: 49000 | Q9: 55000
A10: Kavita Menon | B10: South | C10: 48000 | D10: 51000 | E10: 47000 | F10: 106 | G10: =SUM(C10:E10) -> 146000 | H10: EVEN | J10: 493968.24 | M10: =AVERAGE(C10:E10) -> 48666.667 | O10: 146000 | P10: 51000 | Q10: 48000
A11: Suresh Pillai | B11: East | C11: 39000 | D11: 42500 | E11: 44000 | F11: 107 | G11: =SUM(C11:E11) -> 125500 | H11: ODD | J11: 418075.49 | M11: =AVERAGE(C11:E11) -> 41833.333 | O11: 125500 | P11: 43000 | Q11: 39000
A12: Neha Gupta | B12: West | C12: 66000 | D12: 64000 | E12: 69000 | F12: 108 | G12: =SUM(C12:E12) -> 199000 | H12: EVEN | J12: 695001.14 | M12: =AVERAGE(C12:E12) -> 66333.333 | O12: 199000 | P12: 64000 | Q12: 66000
A13: Arvind Nair | B13: North | C13: 51000 | D13: 53500 | E13: 50000 | F13: 109 | G13: =SUM(C13:E13) -> 154500 | H13: ODD | J13: 525767.4 | M13: =AVERAGE(C13:E13) -> 51500 | O13: 154500 | P13: 54000 | Q13: 51000
A14: Bhavna Shah | B14: South | C14: 44000 | D14: 46500 | E14: 48000 | F14: 110 | G14: =SUM(C14:E14) -> 138500 | H14: EVEN | J14: 466067.02 | M14: =AVERAGE(C14:E14) -> 46166.667 | O14: 138500 | P14: 47000 | Q14: 44000
A16: QUESTIONS
A17: Q1. calculate each sales rep's total sales for Jan+Feb+Mar.
A18: Q2. Use formula to calculate the total January sales made by reps in the 'North' region only.
A19: Q3. Use formula to calculate total February sales for reps in the 'South' region whose January sales exceeded Rs. 45,000.
A20: Q4.find the average total quarterly sales across all sales reps.
A21: Q5. find the average March sales for the 'East' region only.
A22: Q6. Use ROUND to round each rep's total sales to the nearest hundred (2 significant places from the right).
A23: Q7. Use ROUNDUP to round February sales up to the nearest thousand, and ROUNDDOWN to round January sales down to the nearest thousand.
A24: Q8. Use MAX and MIN to identify the highest and lowest total quarterly sales, and INDEX+MATCH (or a simple lookup) to name the top performer.
A25: Q9. Use MOD to check whether each Employee ID is odd or even (Hint: MOD(EmpID,2)=0 means even).
A26: Q10. The company offers a 5% year-end bonus compounded for 2 years on the total sales. Use POWER to calculate (Total*(1.05)^2), and SQRT to find the square root of the highest total sales figure.

Sheet LOGICAL QS
A1: TOPIC 3: LOGICAL FUNCTIONS (AND / OR / NOT)
A3: Dataset: Personal Loan Eligibility Screening — Trustworthy Bank Ltd.
A4: App. ID | B4: Applicant Name | C4: Age | D4: Monthly Income (Rs.) | E4: Credit Score | F4: Existing Loan (Y/N) | G4: AGE - INCOME ELIGIBILITY | H4: PRIORITY REVIEW | I4: NO EXISTING LOANS | J4: APPROVAL | K4: AGE,INCOME,CREDIT SCORE | L4: SPECIAL SENIOR SCHEME
A5: APP101 | B5: Karan Malhotra | C5: 29 | D5: 42000 | E5: 720 | F5: No | G5: =IF(AND(C5>=21,D5>=25000),"ELIGIBLE","NOT ELIGIBLE") -> ELIGIBLE | H5: =IF(OR(E5<=620,F5="YES"),"YES","NO") -> NO | I5: =IF(NOT(F5="YES"),"NO","YES") -> NO | J5: =IF(AND(C5>=21,C5<=60,OR(D5>=25000,E5>750)),"APPROVED","REJECTED") -> APPROVED | K5: =IF(AND(C5>=21,D5>=25000,E5>=650),"SATISFIED","NOTSATISFIED") -> SATISFIED | L5: =IF(AND(C5>=60,I5="NO"),"SPECIAL SENIOR SCHEME","-") -> -
A6: APP102 | B6: Sana Sheikh | C6: 34 | D6: 28000 | E6: 610 | F6: Yes | G6: =IF(AND(C6>=21,D6>=25000),"ELIGIBLE","NOT ELIGIBLE") -> ELIGIBLE | H6: =IF(OR(E6<=620,F6="YES"),"YES","NO") -> YES | I6: =IF(NOT(F6="YES"),"NO","YES") -> YES | J6: =IF(AND(C6>=21,C6<=60,OR(D6>=25000,E6>750)),"APPROVED","REJECTED") -> APPROVED | K6: =IF(AND(C6>=21,D6>=25000,E6>=650),"SATISFIED","NOTSATISFIED") -> NOTSATISFIED | L6: =IF(AND(C6>=60,I6="NO"),"SPECIAL SENIOR SCHEME","-") -> -
A7: APP103 | B7: Vikram Chawla | C7: 45 | D7: 95000 | E7: 790 | F7: No | G7: =IF(AND(C7>=21,D7>=25000),"ELIGIBLE","NOT ELIGIBLE") -> ELIGIBLE | H7: =IF(OR(E7<=620,F7="YES"),"YES","NO") -> NO | I7: =IF(NOT(F7="YES"),"NO","YES") -> NO | J7: =IF(AND(C7>=21,C7<=60,OR(D7>=25000,E7>750)),"APPROVED","REJECTED") -> APPROVED | K7: =IF(AND(C7>=21,D7>=25000,E7>=650),"SATISFIED","NOTSATISFIED") -> SATISFIED | L7: =IF(AND(C7>=60,I7="NO"),"SPECIAL SENIOR SCHEME","-") -> -
A8: APP104 | B8: Lata Desai | C8: 19 | D8: 15000 | E8: 550 | F8: No | G8: =IF(AND(C8>=21,D8>=25000),"ELIGIBLE","NOT ELIGIBLE") -> NOT ELIGIBLE | H8: =IF(OR(E8<=620,F8="YES"),"YES","NO") -> YES | I8: =IF(NOT(F8="YES"),"NO","YES") -> NO | J8: =IF(AND(C8>=21,C8<=60,OR(D8>=25000,E8>750)),"APPROVED","REJECTED") -> REJECTED | K8: =IF(AND(C8>=21,D8>=25000,E8>=650),"SATISFIED","NOTSATISFIED") -> NOTSATISFIED | L8: =IF(AND(C8>=60,I8="NO"),"SPECIAL SENIOR SCHEME","-") -> -
A9: APP105 | B9: Imran Ali | C9: 52 | D9: 60000 | E9: 640 | F9: Yes | G9: =IF(AND(C9>=21,D9>=25000),"ELIGIBLE","NOT ELIGIBLE") -> ELIGIBLE | H9: =IF(OR(E9<=620,F9="YES"),"YES","NO") -> YES | I9: =IF(NOT(F9="YES"),"NO","YES") -> YES | J9: =IF(AND(C9>=21,C9<=60,OR(D9>=25000,E9>750)),"APPROVED","REJECTED") -> APPROVED | K9: =IF(AND(C9>=21,D9>=25000,E9>=650),"SATISFIED","NOTSATISFIED") -> NOTSATISFIED | L9: =IF(AND(C9>=60,I9="NO"),"SPECIAL SENIOR SCHEME","-") -> -
A10: APP106 | B10: Ritu Bhatia | C10: 26 | D10: 31000 | E10: 705 | F10: No | G10: =IF(AND(C10>=21,D10>=25000),"ELIGIBLE","NOT ELIGIBLE") -> ELIGIBLE | H10: =IF(OR(E10<=620,F10="YES"),"YES","NO") -> NO | I10: =IF(NOT(F10="YES"),"NO","YES") -> NO | J10: =IF(AND(C10>=21,C10<=60,OR(D10>=25000,E10>750)),"APPROVED","REJECTED") -> APPROVED | K10: =IF(AND(C10>=21,D10>=25000,E10>=650),"SATISFIED","NOTSATISFIED") -> SATISFIED | L10: =IF(AND(C10>=60,I10="NO"),"SPECIAL SENIOR SCHEME","-") -> -
A11: APP107 | B11: Sameer Joshi | C11: 63 | D11: 48000 | E11: 680 | F11: No | G11: =IF(AND(C11>=21,D11>=25000),"ELIGIBLE","NOT ELIGIBLE") -> ELIGIBLE | H11: =IF(OR(E11<=620,F11="YES"),"YES","NO") -> NO | I11: =IF(NOT(F11="YES"),"NO","YES") -> NO | J11: =IF(AND(C11>=21,C11<=60,OR(D11>=25000,E11>750)),"APPROVED","REJECTED") -> REJECTED | K11: =IF(AND(C11>=21,D11>=25000,E11>=650),"SATISFIED","NOTSATISFIED") -> SATISFIED | L11: =IF(AND(C11>=60,I11="NO"),"SPECIAL SENIOR SCHEME","-") -> SPECIAL SENIOR SCHEME
A12: APP108 | B12: Anjali Kulkarni | C12: 38 | D12: 27000 | E12: 760 | F12: Yes | G12: =IF(AND(C12>=21,D12>=25000),"ELIGIBLE","NOT ELIGIBLE") -> ELIGIBLE | H12: =IF(OR(E12<=620,F12="YES"),"YES","NO") -> YES | I12: =IF(NOT(F12="YES"),"NO","YES") -> YES | J12: =IF(AND(C12>=21,C12<=60,OR(D12>=25000,E12>750)),"APPROVED","REJECTED") -> APPROVED | K12: =IF(AND(C12>=21,D12>=25000,E12>=650),"SATISFIED","NOTSATISFIED") -> SATISFIED | L12: =IF(AND(C12>=60,I12="NO"),"SPECIAL SENIOR SCHEME","-") -> -
A13: APP109 | B13: Tarun Reddy | C13: 24 | D13: 22000 | E13: 590 | F13: No | G13: =IF(AND(C13>=21,D13>=25000),"ELIGIBLE","NOT ELIGIBLE") -> NOT ELIGIBLE | H13: =IF(OR(E13<=620,F13="YES"),"YES","NO") -> YES | I13: =IF(NOT(F13="YES"),"NO","YES") -> NO | J13: =IF(AND(C13>=21,C13<=60,OR(D13>=25000,E13>750)),"APPROVED","REJECTED") -> REJECTED | K13: =IF(AND(C13>=21,D13>=25000,E13>=650),"SATISFIED","NOTSATISFIED") -> NOTSATISFIED | L13: =IF(AND(C13>=60,I13="NO"),"SPECIAL SENIOR SCHEME","-") -> -
A14: APP110 | B14: Pooja Agarwal | C14: 41 | D14: 110000 | E14: 800 | F14: No | G14: =IF(AND(C14>=21,D14>=25000),"ELIGIBLE","NOT ELIGIBLE") -> ELIGIBLE | H14: =IF(OR(E14<=620,F14="YES"),"YES","NO") -> NO | I14: =IF(NOT(F14="YES"),"NO","YES") -> NO | J14: =IF(AND(C14>=21,C14<=60,OR(D14>=25000,E14>750)),"APPROVED","REJECTED") -> APPROVED | K14: =IF(AND(C14>=21,D14>=25000,E14>=650),"SATISFIED","NOTSATISFIED") -> SATISFIED | L14: =IF(AND(C14>=60,I14="NO"),"SPECIAL SENIOR SCHEME","-") -> -
A16: QUESTIONS
A17: Q1. Bank policy: an applicant is 'Age-Income Eligible' only if Age is 21 or above AND Monthly Income is Rs. 25,000 or above. Write a formula using AND to return TRUE/FALSE.
A18: Q2. Applicants need a 'Priority Review' if their Credit Score is below 620 OR they already have an existing loan. Write a formula using OR.
A19: Q3. Write a formula using NOT to flag applicants who do NOT have an existing loan (result should be TRUE for 'No').
A20: Q4. Combine IF, AND and OR: an applicant is 'Approved' if (Age is between 21 and 60 inclusive) AND (Income >= 25000 OR Credit Score > 750); otherwise 'Rejected'.
A21: Q5. Write a formula using AND with three conditions to check if an applicant simultaneously has Age>=21, Income>=25000, and Credit Score>=650.
A22: Q6. Senior citizens (Age > 60) with no existing loan get a 'Special Senior Scheme' offer. Write a nested formula using IF and AND to display this remark.

Sheet FIND AND SEARCH QS
A1: TOPIC 7: FIND & SEARCH FUNCTIONS
A3: Dataset: Employee Contact Directory — Skyline Corp HR Department
A4: Employee Name | B4: Email Address | C4: Full Address | D4: Username (Q2) | E4: Domain (Q4) | F4: City (Q6) | G4: @ | H4: GMAIL
A5: Nikhil Rane | B5: nikhil.rane@gmail.com | C5: 204, MG Road, Pune, 411001 | D5: nikhil.rane | E5: =RIGHT(B5,LEN(B5)-FIND("@",B5)) -> gmail.com | F5: PUNE | G5: {=FIND("@",B5:B10)} -> 12 | H5: =IF(ISNUMBER(SEARCH("gmail",B5)),"YES","NO") -> YES | I5: =LEFT(C5,FIND(",",C5)-1) -> 204
A6: Sarah MATHEW | B6: sarah.mathew@OUTLOOK.com | C6: 12, Park Street, Kolkata, 700016 | D6: sarah.mathew | E6: =RIGHT(B6,LEN(B6)-FIND("@",B6)) -> OUTLOOK.com | F6: . | G6: 13 | H6: =IF(ISNUMBER(SEARCH("gmail",B6)),"YES","NO") -> NO | I6: =LEFT(C6,FIND(",",C6)-1) -> 12
A7: Farhan Sheikh | B7: farhan.s@yahoo.co.in | C7: 45, Anna Salai, Chennai, 600002 | D7: farhan.s | E7: =RIGHT(B7,LEN(B7)-FIND("@",B7)) -> yahoo.co.in | F7: CHENNAI | G7: 9 | H7: =IF(ISNUMBER(SEARCH("gmail",B7)),"YES","NO") -> NO | I7: =LEFT(C7,FIND(",",C7)-1) -> 45
A8: Divya Krishnan | B8: divya.k@gmail.com | C8: 7, Residency Road, Bengaluru, 560025 | D8: divya.k | E8: =RIGHT(B8,LEN(B8)-FIND("@",B8)) -> gmail.com | F8: BENGALURU | G8: 8 | H8: =IF(ISNUMBER(SEARCH("gmail",B8)),"YES","NO") -> YES | I8: =LEFT(C8,FIND(",",C8)-1) -> 7
A9: Om Prakash | B9: om.prakash@COMPANYMAIL.com | C9: 19, Civil Lines, Nagpur, 440001 | D9: om.prakash | E9: =RIGHT(B9,LEN(B9)-FIND("@",B9)) -> COMPANYMAIL.com | F9: NAGPUR | G9: 11 | H9: =IF(ISNUMBER(SEARCH("gmail",B9)),"YES","NO") -> NO | I9: =LEFT(C9,FIND(",",C9)-1) -> 19
A10: Leena D'Souza | B10: leena.ds@gmail.com | C10: 88, Linking Road, Mumbai, 400050 | D10: leena.ds | E10: =RIGHT(B10,LEN(B10)-FIND("@",B10)) -> gmail.com | F10: MUMBAI | G10: 9 | H10: =IF(ISNUMBER(SEARCH("gmail",B10)),"YES","NO") -> YES | I10: =LEFT(C10,FIND(",",C10)-1) -> 88
A12: QUESTIONS
A13: Q1. Use FIND to return the position (character number) of the '@' symbol within each Email Address.
A14: Q2. Use MID together with FIND to extract the 'Username' portion of the email (the text before '@').
A15: Q3. One employee's email contains 'OUTLOOK' in uppercase. Use SEARCH (which is case-insensitive) to check if the text 'gmail' appears anywhere in each email — compare this to using FIND for the same check on 'GMAIL' and explain the difference in results.
A16: Q4. Use RIGHT combined with LEN and FIND to extract the 'Domain' portion of the email (the text after '@').
A17: Q5. In the 'Full Address' column, use FIND to locate the position of the first comma, then use LEFT to extract the house/street portion before it.
A18: Q6. Use FIND (with nested FIND/SUBSTITUTE as needed) to extract the 'City' name, which appears between the 2nd and 3rd commas in the Full Address.

Sheet DATE&TIME
A1: TOPIC 9: DATE & TIME FUNCTIONS
A3: Dataset A: Employee Attendance Log — 18 Aug 2026
A4: Employee | B4: Date of Joining | C4: Check-In | D4: Check-Out | E4: Hours Worked (Q9) | F4: Tenure in Days (Q1) | G4: Day of Week (Q6) | H4: DATE DIFF
A5: Rahul Batra | B5: 43536 | C5: 0.38541667 | D5: 0.75347222 | E5: =D5-C5 -> 0.36805556 | F5: =TODAY()-B5 -> 2776 | G5: =TEXT(B5,"DDDD") -> Tuesday
A6: Simran Kaur | B6: 44378 | C6: 0.40277778 | D6: 0.74305556 | E6: =D6-C6 -> 0.34027778 | F6: =TODAY()-B6 -> 1934 | G6: =TEXT(B6,"DDDD") -> Thursday
A7: Devendra Rao | B7: 43062 | C7: 0.37847222 | D7: 0.79166667 | E7: =D7-C7 -> 0.41319444 | F7: =TODAY()-B7 -> 3250 | G7: =TEXT(B7,"DDDD") -> Thursday
A8: Ayesha Siddiqui | B8: 44935 | C8: 0.41666667 | D8: 0.77083333 | E8: =D8-C8 -> 0.35416667 | F8: =TODAY()-B8 -> 1377 | G8: =TEXT(B8,"DDDD") -> Monday
A9: Manish Pillai | B9: 43969 | C9: 0.39236111 | D9: 0.75694444 | E9: =D9-C9 -> 0.36458333 | F9: =TODAY()-B9 -> 2343 | G9: =TEXT(B9,"DDDD") -> Monday
A12: Dataset B: Project Timeline — Website Revamp Project
A13: Task | B13: Start Date | C13: End Date | D13: Working Days (Q3) | E13: 10-Workday Deadline (Q4) | F13: Probation/Review +3mo (Q7) | G13: Month-End (Q8) | H13: YEAR | I13: MONTH | J13: DAY
A14: Requirement Gathering | B14: 46266 | C14: 46275 | D14: =NETWORKDAYS(B14,C14) -> 8 | E14: =WORKDAY(B14,10) -> 46280 | F14: =EDATE(B14,3) -> 46357 | G14: =EOMONTH(B14,0) -> 46295 | H14: =YEAR(B14) -> 2026 | I14: =MONTH(B14) -> 9 | J14: =DAY(B14) -> 1
A15: UI/UX Design | B15: 46276 | C15: 46290 | D15: =NETWORKDAYS(B15,C15) -> 11 | E15: =WORKDAY(B15,10) -> 46290 | F15: =EDATE(B15,3) -> 46367 | G15: =EOMONTH(B15,0) -> 46295 | H15: =YEAR(B15) -> 2026 | I15: =MONTH(B15) -> 9 | J15: =DAY(B15) -> 11
A16: Development | B16: 46291 | C16: 46315 | D16: =NETWORKDAYS(B16,C16) -> 17 | E16: =WORKDAY(B16,10) -> 46304 | F16: =EDATE(B16,3) -> 46382 | G16: =EOMONTH(B16,0) -> 46295 | H16: =YEAR(B16) -> 2026 | I16: =MONTH(B16) -> 9 | J16: =DAY(B16) -> 26
A17: Testing | B17: 46316 | C17: 46326 | D17: =NETWORKDAYS(B17,C17) -> 8 | E17: =WORKDAY(B17,10) -> 46330 | F17: =EDATE(B17,3) -> 46408 | G17: =EOMONTH(B17,0) -> 46326 | H17: =YEAR(B17) -> 2026 | I17: =MONTH(B17) -> 10 | J17: =DAY(B17) -> 21
A20: QUESTIONS
A21: Q1. Using Dataset A, calculate each employee's 'Tenure in Days' as TODAY() minus their Date of Joining.
A22: Q2. Extend Q1: use DATEDIF to express each employee's tenure in complete YEARS and MONTHS (e.g., '7 years 5 months').
A23: Q3. Using Dataset B, use NETWORKDAYS to calculate the number of working days (excluding weekends) between each task's Start Date and End Date.
A24: Q4. Using Dataset B, use WORKDAY to calculate the deadline date that falls exactly 10 working days after each task's Start Date.
A25: Q5. Use YEAR, MONTH, and DAY to extract each of these components separately from the 'Start Date' column in Dataset B.
A26: Q6. Use WEEKDAY (or TEXT with a date format) to determine the day of the week (e.g., Monday, Tuesday) for each employee's Date of Joining in Dataset A.
A27: Q7. New employees must complete a 3-month probation. Use EDATE to calculate the 'Probation Review Date' as 3 months after each task's Start Date in Dataset B.
A28: Q8. Use EOMONTH to find the last date of the month in which each task in Dataset B starts.
A29: Q9. Using Dataset A, calculate 'Hours Worked' as Check-Out time minus Check-In time, formatted to show hours and minutes.

Sheet REF..
A1: TOPIC 8: REFERENCE FUNCTIONS (INDEX / MATCH / OFFSET / INDIRECT / ROW / COLUMN)
A3: Dataset: 6-Month Sales Matrix — Product vs Month (Units Sold), Table starts at A5
A4: Product | B4: Jan | C4: Feb | D4: Mar | E4: Apr | F4: May | G4: Jun
A5: Widget A | B5: 120 | C5: 135 | D5: 128 | E5: 140 | F5: 150 | G5: 145 | H5: =INDEX(B5:G9,3,4) -> 220 | I5: =MAX(G5:G9) -> 225
A6: Widget B | B6: 95 | C6: 102 | D6: 110 | E6: 98 | F6: 115 | G6: 120 | H6: =MATCH("Apr",B4:G4,0) -> 4
A7: Widget C | B7: 200 | C7: 210 | D7: 195 | E7: 220 | F7: 230 | G7: 225 | H7: =INDEX(B5:G9,2,5) -> 115
A8: Widget D | B8: 60 | C8: 58 | D8: 65 | E8: 70 | F8: 68 | G8: 75 | H8: =OFFSET(B5,2,3) -> 220
A9: Widget E | B9: 150 | C9: 148 | D9: 160 | E9: 155 | F9: 165 | G9: 170 | H9: {=INDIRECT(A1&B1)} -> #REF!
A11: QUESTIONS
H12: =ROW()-ROW($A$5)+1 -> 8
A13: Q2. Use MATCH to find which column number 'Apr' occupies within the header row.
A14: Q3. Combine INDEX and MATCH to look up the sales of 'Widget B' in 'May' without hardcoding row or column numbers.
A15: Q4. Starting from the 'Widget A / Jan' cell as the reference point, use OFFSET to retrieve the value that is 2 rows down and 3 columns right of it. Which product/month does this correspond to?
A16: Q5. Use INDIRECT to build a cell reference dynamically from text, e.g. combine a row number and column letter typed in separate cells to fetch a value from the table.
A17: Q6. Use ROW() and COLUMN() to auto-generate a serial number list (1, 2, 3...) next to the Product column without typing the numbers manually.
A18: Q7. Use INDEX + MATCH (for the row) with the MAX function to find the product name with the highest sales in 'Jun', and use ADDRESS to return that cell's address.

Sheet LOOKUP QS
A1: TOPIC 4: LOOKUP FUNCTIONS (VLOOKUP / HLOOKUP / INDEX-MATCH)
A3: Dataset A: Product Master — Zenith Electronics Store
A4: ProductID | B4: Product Name | C4: Category | D4: Unit Price (Rs.)
A5: P001 | B5: LED Bulb 9W | C5: Lighting | D5: 120
A6: P002 | B6: Ceiling Fan | C6: Appliances | D6: 1850
A7: P003 | B7: USB Cable | C7: Accessories | D7: 199
A8: P004 | B8: Bluetooth Speaker | C8: Electronics | D8: 1499
A9: P005 | B9: Wall Clock | C9: Home Decor | D9: 350
A10: P006 | B10: Extension Board | C10: Accessories | D10: 450
A11: P007 | B11: Table Lamp | C11: Lighting | D11: 699
A12: P008 | B12: Mixer Grinder | C12: Appliances | D12: 2999
A15: Dataset B: Order Details (Order Day — 14 Aug 2026)
A16: OrderID | B16: ProductID | C16: Quantity | D16: Product Name (Q1) | E16: Unit Price (Q2) | F16: Total Amount (Q3)
A17: ORD-501 | B17: P003 | C17: 5 | D17: =VLOOKUP(B5,A5:A12,2,FALSE) -> #N/A
A18: ORD-502 | B18: P002 | C18: 2
A19: ORD-503 | B19: P006 | C19: 8
A20: ORD-504 | B20: P008 | C20: 1
A21: ORD-505 | B21: P001 | C21: 12
A22: ORD-506 | B22: P004 | C22: 3
A25: Dataset C: Quantity-based Discount Slabs (for approximate-match VLOOKUP)
A26: Min Qty | B26: Discount %
A27: 0 | B27: 0%
A28: 5 | B28: 5%
A29: 10 | B29: 10%
A30: 20 | B30: 15%
A33: Dataset D: Two-way Matrix — Region-wise Monthly Revenue (Rs. '000)
A34: Region | B34: Jan | C34: Feb | D34: Mar | E34: Apr
A35: North | B35: 320 | C35: 340 | D35: 310 | E35: 360
A36: South | B36: 410 | C36: 400 | D36: 430 | E36: 420
A37: East | B37: 280 | C37: 300 | D37: 295 | E37: 310
A38: West | B38: 350 | C38: 365 | D38: 355 | E38: 370
A41: QUESTIONS
A42: Q1. In Dataset B, use VLOOKUP to fetch the 'Product Name' for each OrderID by looking up ProductID in Dataset A.
A43: Q2. Use VLOOKUP to fetch the 'Unit Price' for each order, then calculate 'Total Amount' as Unit Price x Quantity.
A44: Q3. Rewrite Question 1 using INDEX + MATCH instead of VLOOKUP, and confirm you get the same product names.
A45: Q4. Use VLOOKUP with an APPROXIMATE match (TRUE / 1) on Dataset C to find the discount % applicable to an order with Quantity=8 and Quantity=15.
A46: Q5. Using Dataset D, write an HLOOKUP formula to find North region's revenue for 'Mar'.
A47: Q6. Using Dataset D, write an INDEX + MATCH + MATCH (two-way lookup) formula to find the revenue for Region='East' and Month='Feb' without hardcoding row/column numbers.
A48: Q7. A customer asks: 'What product costs exactly Rs. 1499?' Write a formula (INDEX+MATCH or VLOOKUP with a helper) to return the Product Name for a given Unit Price.

Sheet RANK QS
A1: TOPIC 5: RANK FUNCTION
A3: Dataset: District Athletics Meet — 100m Sprint & Overall Points
A4: Athlete | B4: School | C4: 100m Time (sec) | D4: Rank by Time (Q1) | E4: Points Scored | F4: Rank by Points (Q2) | H4: MEDAL
A5: Rahul Verma | B5: St. Xavier's | C5: 11.8 | D5: =RANK(C5,$C$5:$C$12,1) -> 2 | E5: 87 | F5: =RANK(E5,$E$5:$E$12,0) -> 5 | G5: =LARGE(E5:E12,3) -> 91 | H5: =IF(F5=1,"GOLD MEDAL",IF(F5=2,"SILVER MEDAL",IF(F5=3,"BRONZE MEDAL","--"))) -> --
A6: Fatima Sheikh | B6: DPS | C6: 12.4 | D6: =RANK(C6,$C$5:$C$12,1) -> 6 | E6: 91 | F6: =RANK(E6,$E$5:$E$12,0) -> 2 | G6: =SMALL(C5:C12,3) -> 11.9 | H6: =IF(F6=1,"GOLD MEDAL",IF(F6=2,"SILVER MEDAL",IF(F6=3,"BRONZE MEDAL","--"))) -> SILVER MEDAL
A7: Ganesh Naidu | B7: Ryan Intl. | C7: 11.5 | D7: =RANK(C7,$C$5:$C$12,1) -> 1 | E7: 95 | F7: =RANK(E7,$E$5:$E$12,0) -> 1 | G7: =_xlfn.RANK.EQ(E5,$E$5:$E$12,0) -> 5 | H7: =IF(F7=1,"GOLD MEDAL",IF(F7=2,"SILVER MEDAL",IF(F7=3,"BRONZE MEDAL","--"))) -> GOLD MEDAL
A8: Aisha Khan | B8: St. Xavier's | C8: 12.9 | D8: =RANK(C8,$C$5:$C$12,1) -> 8 | E8: 78 | F8: =RANK(E8,$E$5:$E$12,0) -> 8 | H8: =IF(F8=1,"GOLD MEDAL",IF(F8=2,"SILVER MEDAL",IF(F8=3,"BRONZE MEDAL","--"))) -> --
A9: Suresh Yadav | B9: DPS | C9: 12.1 | D9: =RANK(C9,$C$5:$C$12,1) -> 4 | E9: 84 | F9: =RANK(E9,$E$5:$E$12,0) -> 6 | H9: =IF(F9=1,"GOLD MEDAL",IF(F9=2,"SILVER MEDAL",IF(F9=3,"BRONZE MEDAL","--"))) -> --
A10: Neha Thakur | B10: Ryan Intl. | C10: 11.9 | D10: =RANK(C10,$C$5:$C$12,1) -> 3 | E10: 91 | F10: =RANK(E10,$E$5:$E$12,0) -> 2 | H10: =IF(F10=1,"GOLD MEDAL",IF(F10=2,"SILVER MEDAL",IF(F10=3,"BRONZE MEDAL","--"))) -> SILVER MEDAL
A11: Vikas Bansal | B11: Delhi Public | C11: 12.6 | D11: =RANK(C11,$C$5:$C$12,1) -> 7 | E11: 80 | F11: =RANK(E11,$E$5:$E$12,0) -> 7 | H11: =IF(F11=1,"GOLD MEDAL",IF(F11=2,"SILVER MEDAL",IF(F11=3,"BRONZE MEDAL","--"))) -> --
A12: Rina Kapoor | B12: St. Xavier's | C12: 12.2 | D12: =RANK(C12,$C$5:$C$12,1) -> 5 | E12: 88 | F12: =RANK(E12,$E$5:$E$12,0) -> 4 | H12: =IF(F12=1,"GOLD MEDAL",IF(F12=2,"SILVER MEDAL",IF(F12=3,"BRONZE MEDAL","--"))) -> --
A14: QUESTIONS
A15: Q1. In 100m sprint, LOWER time is better. Use RANK (with the correct order argument) to rank athletes by 'Time' from fastest to slowest.
A16: Q2. For overall 'Points Scored', HIGHER is better. Use RANK to rank athletes from highest to lowest points.
A17: Q3. Use the LARGE function to find the 2nd highest points scored in the tournament.
A18: Q4. Use the SMALL function to find the 3rd fastest (lowest) 100m time.
A19: Q5. Notice that two athletes (Fatima Sheikh and Neha Thakur) are tied at 91 points. Use RANK.EQ to rank them, then explain using RANK.AVG how the rank would differ for tied values.
A20: Q6. Write a formula combining IF and RANK that displays "Gold Medal" for Rank 1, "Silver Medal" for Rank 2, "Bronze Medal" for Rank 3, and blank otherwise (based on Points rank).

Sheet misc.qs
A1: TOPIC 6: MISCELLANEOUS FUNCTIONS (COUNT family, SUMPRODUCT, TEXT)
A3: Dataset: Warehouse Inventory — FreshMart Distribution Center
A4: Item Code | B4: Item Name | C4: Category | D4: Stock Qty | E4: Reorder Level | F4: Unit Price (Rs.) | G4: Notes | H4: Q1 | I4: Q2 | J4: Q3 | K4: Q4 | L4: Q5 | M4: Q7 | N4: Q8
A5: itm-001 | B5: rice bag 25kg | C5: Grocery | D5: 40 | E5: 20 | F5: 850 | H5: {=SUMPRODUCT(--(D5:D12<E5:E12))} -> 4 | I5: =COUNTIFS(C5:C12,"ELECTRONICS",D5:D12,0) -> 2 | J5: =COUNTA(B5:B12) -> 7 | K5: =COUNTBLANK(B5:B12) -> 1 | L5: =SUMPRODUCT(D5:D12,F5:F12) -> 55900 | M5: =A5&" - "&B5 -> itm-001 - rice bag 25kg
A6: ITM-002 | B6: Cooking Oil 5L | C6: Grocery | D6: 8 | E6: 15 | F6: 620 | M6: =A6&" - "&B6 -> ITM-002 - Cooking Oil 5L | N6: =UPPER(TRIM(A6)) -> ITM-002
A7: ITM-003 | B7: LED Tube Light | C7: Electronics | D7: 0 | E7: 10 | F7: 210 | M7: =A7&" - "&B7 -> ITM-003 - LED Tube Light | N7: =UPPER(TRIM(A7)) -> ITM-003
A8: ITM-004 | B8: Notebook Pack | C8: Stationery | D8: 65 | E8: 30 | F8: 140 | M8: =A8&" - "&B8 -> ITM-004 - Notebook Pack | N8: =UPPER(TRIM(A8)) -> ITM-004
A9: ITM-005 | B9: wireless mouse | C9: Electronics | D9: 5 | E9: 12 | F9: 550 | M9: =A9&" - "&B9 -> ITM-005 - wireless mouse | N9: =UPPER(TRIM(A9)) -> ITM-005
A10: ITM-006 | B10: Detergent 1kg | C10: Grocery | D10: 22 | E10: 20 | F10: 95 | M10: =A10&" - "&B10 -> ITM-006 - Detergent 1kg | N10: =UPPER(TRIM(A10)) -> ITM-006
A11: ITM-007 | C11: Electronics | D11: 0 | E11: 10 | F11: 999 | M11: =A11&" - "&B11 -> ITM-007 - | N11: =UPPER(TRIM(A11)) -> ITM-007
A12: ITM-008 | B12: ball pen box | C12: Stationery | D12: 50 | E12: 25 | F12: 60 | M12: =A12&" - "&B12 -> ITM-008 - ball pen box | N12: =UPPER(TRIM(A12)) -> ITM-008
A14: QUESTIONS
A15: Q1. count how many items currently have Stock Qty BELOW their Reorder Level (i.e., need restocking).
A16: Q2. count items in the 'Electronics' category that have Stock Qty equal to 0 (out of stock).
A17: Q3. count the number of non-blank entries in the 'Item Name' column (note: one item name is missing).
A18: Q4. count how many cells are blank in the 'Item Name' column.
A19: Q5. calculate the total inventory value (Stock Qty x Unit Price) for the entire warehouse in a single formula.
A20: Q6. Use the & operator or CONCATENATE to create a combined 'Label' text such as 'ITM-001 - Rice Bag 25kg' for each row.
A21: Q7. Item names have inconsistent capitalization. Use PROPER (or UPPER/LOWER) to standardize all item names to Proper Case in a new column.
A22: Q8. Some Item Codes have extra leading/trailing spaces (e.g., ' itm-001'). Use TRIM combined with UPPER to clean and standardize them.

Sheet Scenario Summary
B2: Scenario Summary
D3: Current Values: | E3: Best case | F3: Worst case | G3: Most Likely
E4: Created by software on 29-09-2026 | F4: Created by software on 29-09-2026 | G4: Created by software on 29-09-2026
B5: Changing Cells:
C6: $B$11 | D6: 1000 | E6: 1400 | F6: 650 | G6: 1000
C7: $B$12 | D7: 850 | E7: 900 | F7: 780 | G7: 850
B8: Result Cells:
C9: $B$15 | D9: 150000 | E9: 352000 | F9: -11000 | G9: 150000
B10: Notes: Current Values column represents values of changing cells at
B11: time Scenario Summary Report was created. Changing cells for each
B12: scenario are highlighted in gray.

Sheet what if qs
A1: TOPIC 10: WHAT-IF ANALYSIS (Goal Seek / Data Table / Scenario Manager)
G2: 0.07 | H2: =B7 -> 25000
A3: Dataset A: Home Loan EMI Calculator — Trustworthy Bank Ltd. | G3: 0.075 | H3: 23567.552
A4: Loan Amount (Rs.) | B4: 2500000 | G4: 0.08 | H4: 24278.303
A5: Annual Interest Rate | B5: 0.085 | G5: 0.085 | H5: 25000
A6: Tenure (Years) | B6: 14.547087 | G6: 0.09 | H6: 25732.454
A7: Monthly EMI | B7: =-PMT(B5/12,B6*12,B4) -> 25000 | G7: 0.095 | H7: 26475.468
G8: 0.1 | H8: 27228.841
A9: Dataset B: Monthly Sales & Profit Planning — Sunrise Retail Stores | G9: 0.105 | H9: 27992.365
A10: Assumption | B10: Base Case Value | G10: 0.11 | H10: 28765.827
A11: Units Sold per Month | B11: 2060.6061
A12: Selling Price per Unit (Rs.) | B12: 850
A13: Variable Cost per Unit (Rs.) | B13: 520 | G13: =B7 -> 25000 | H13: 0.07 | I13: 0.075 | J13: 0.08 | K13: 0.085 | L13: 0.09 | M13: 0.095 | N13: 0.1 | O13: 0.105 | P13: 0.11
A14: Fixed Monthly Cost (Rs.) | B14: 180000 | G14: 10 | H14: 25000 | I14: 25000 | J14: 25000 | K14: 25000 | L14: 25000 | M14: 25000 | N14: 25000 | O14: 25000 | P14: 25000
A15: Monthly Profit (Rs.) | G15: 15 | H15: 25000 | I15: 25000 | J15: 25000 | K15: 25000 | L15: 25000 | M15: 25000 | N15: 25000 | O15: 25000 | P15: 25000
G16: 20 | H16: 25000 | I16: 25000 | J16: 25000 | K16: 25000 | L16: 25000 | M16: 25000 | N16: 25000 | O16: 25000 | P16: 25000
G17: 25 | H17: 25000 | I17: 25000 | J17: 25000 | K17: 25000 | L17: 25000 | M17: 25000 | N17: 25000 | O17: 25000 | P17: 25000
A18: QUESTIONS
A19: Q1. Using Dataset A, the bank's PMT-based EMI formula is already entered. Use GOAL SEEK to find the Tenure (in years) required to bring the Monthly EMI down to exactly Rs. 25,000 (keep Loan Amount and Interest Rate fixed). Describe the exact Goal Seek dialog values you would set (Set cell / To value / By changing cell).
A20: Q2. Build a ONE-VARIABLE DATA TABLE that shows how the Monthly EMI changes as the Annual Interest Rate varies from 7% to 11% in steps of 0.5% (keep Loan Amount and Tenure fixed). List the Data Table row/column input cell you would use.
A21: Q3. Build a TWO-VARIABLE DATA TABLE that shows Monthly EMI for combinations of Interest Rate (7%–11%) across the columns and Tenure (10, 15, 20, 25 years) down the rows.
A22: Q4. Using Dataset B, use SCENARIO MANAGER to create three scenarios — 'Best Case' (Units=1400, Price=900), 'Worst Case' (Units=650, Price=780), and 'Most Likely' (values as given) — then generate a Scenario Summary report showing the resulting Monthly Profit for each.
A23: Q5. Using Dataset B, use GOAL SEEK to determine how many Units must be sold per month to achieve a target Monthly Profit of Rs. 5,00,000, keeping Price, Variable Cost and Fixed Cost unchanged.

Sheet data validation qs
A1: TOPIC 11: DATA VALIDATION
A3: Dataset: Online Order Entry Form — QuickCart E-commerce
A4: Order ID | B4: Customer Name | C4: Product Category | D4: Quantity | E4: Delivery Date | F4: Payment Mode | G4: Customer rating
A5: ORD1001 | B5: Ramesh Iyer | C5: Electronics | D5: 2 | E5: 46259 | F5: UPI | G5: 3
A6: ORD1002 | B6: Sneha Kapoor | C6: Clothing | D6: 5 | E6: 46261 | F6: Card | G6: 4
A7: ORD1003 | B7: Aditya Roy | C7: Grocery | D7: 12 | E7: 46258 | F7: Cash | G7: 2
A9: QUESTIONS
A10: Q1. Apply LIST-based Data Validation on the 'Product Category' column restricting entries to: Electronics, Clothing, Grocery, Furniture.
A11: Q2. Apply Data Validation on 'Quantity' to allow only WHOLE NUMBERS between 1 and 50. Set a custom error message: 'Enter a value between 1 and 50'.
A12: Q3. Apply Data Validation on 'Delivery Date' so that only dates AFTER today (TODAY()) can be entered.
A13: Q4. Apply LIST-based Data Validation on 'Payment Mode' restricting entries to: Cash, Card, UPI, NetBanking.
A14: Q5. Apply a CUSTOM FORMULA Data Validation on 'Order ID' that prevents duplicate Order IDs from being entered (Hint: use COUNTIF(range,cell)<=1).
A15: Q6. Apply Data Validation on 'Customer Name' restricting text length to a maximum of 30 characters, and add an Input Message that guides the user before they type.

Sheet conditional qs
A1: TOPIC 12: CONDITIONAL FORMATTING
A3: Dataset: Monthly Sales Target Achievement — Sunrise Retail Stores, Aug 2026
A4: Sales Rep | B4: Target (Rs.) | C4: Achieved (Rs.) | D4: % Achievement
A5: Ravi Kumar | B5: 500000 | C5: 480000 | D5: =C5/B5 -> 0.96
A6: Sunita Rao | B6: 450000 | C6: 510000 | D6: =C6/B6 -> 1.1333333
A7: Manoj Tiwari | B7: 400000 | C7: 350000 | D7: =C7/B7 -> 0.875
A8: Farah Khan | B8: 550000 | C8: 600000 | D8: =C8/B8 -> 1.0909091
A9: Deepak Joshi | B9: 480000 | C9: 460000 | D9: =C9/B9 -> 0.95833333
A10: Kavita Menon | B10: 420000 | C10: 430000 | D10: =C10/B10 -> 1.0238095
A11: Suresh Pillai | B11: 500000 | C11: 300000 | D11: =C11/B11 -> 0.6
A12: Neha Gupta | B12: 470000 | C12: 470000 | D12: =C12/B12 -> 1
A13: Ravi Kumar | B13: 500000 | C13: 495000 | D13: =C13/B13 -> 0.99
A17: QUESTIONS
A18: Q1. Apply Conditional Formatting to highlight (in red fill) every 'Achieved' cell that is LESS THAN the corresponding 'Target' cell.
A19: Q2. Apply a 3-color Color Scale (red-yellow-green) to the '% Achievement' column so low performers show red and high performers show green.
A20: Q3. Apply Data Bars to the 'Achieved' column to visually compare sales figures at a glance.
A21: Q4. Apply an Icon Set (e.g., Traffic Lights) to the '% Achievement' column: green for >=100%, yellow for 80-99%, red for below 80%.
A22: Q5. Notice 'Ravi Kumar' appears twice in the Sales Rep column. Apply Conditional Formatting using 'Highlight Duplicate Values' to flag repeated names.
A23: Q6. Write a FORMULA-BASED conditional formatting rule that highlights the ENTIRE ROW in light green whenever '% Achievement' is 100% or more (Hint: use a formula like =$D5>=1 applied to the full row range).
A24: Q7. Apply Conditional Formatting using 'Top 10%' and 'Bottom 10%' rules on the 'Achieved' column to instantly spot the best and weakest performers.

Sheet Sheet10

Sheet Sheet8
A3: Count of Payment Method | D3: Total sales by each product
A4: Payment Method | B4: Total | D4: Product | E4: Total | G4: Total sales by each region | J4: Monthly sales amount
A5: Cash | B5: 16 | D5: Woolen Sweater | E5: 54 | G5: Region | H5: Total | J5: Months (Order Date) | K5: Total
A6: Credit Card | B6: 11 | D6: Filing Cabinet | E6: 52 | G6: North | H6: 113739 | J6: Aug | K6: 57919
A7: Card | B7: 10 | D7: Sunflower Oil 1L | E7: 40 | G7: West | H7: 98025 | J7: Dec | K7: 55439
A8: Upi | B8: 10 | D8: Green Tea Pack | E8: 35 | G8: East | H8: 88464 | J8: May | K8: 45962
A9: Debit Card | B9: 9 | D9: LED Bulb | E9: 29 | G9: South | H9: 47208 | J9: Apr | K9: 45453
A10: Online | B10: 7 | D10: Bed Frame | E10: 28 | G10: Grand Total | H10: 347436 | J10: Jul | K10: 41264
A11: Online | B11: 5 | D11: USB Cable | E11: 25 | J11: Nov | K11: 27454
A12: Unknown | B12: 2 | D12: Kurta Set | E12: 24 | J12: Jun | K12: 18716
A13: Grand Total | B13: 70 | D13: Basmati Rice 5kg | E13: 16 | G13: Total sales by each category | J13: Mar | K13: 18702
D14: Wheat Flour 5kg | E14: 16 | G14: Category | H14: Total | J14: Oct | K14: 14917
A15: Sum of Sales Amount | D15: Office Chair | E15: 16 | H15: 99133 | J15: Feb | K15: 10785
A16: Payment Method | B16: Total | D16: Gel Pens (10) | E16: 15 | G16: Groceries | H16: 78276 | J16: Jan | K16: 5932
A17: Card | B17: 32789 | D17: Formal Shirt | E17: 14 | G17: Apparel | H17: 62954 | J17: Sep | K17: 4893
A18: Cash | B18: 80944 | D18: Sofa Cushion | E18: 12 | G18: Electronics | H18: 49334 | J18: Grand Total | K18: 347436
A19: Credit Card | B19: 80018 | D19: Sugar 1kg | E19: 12 | G19: Stationaries | H19: 41754
A20: Debit Card | B20: 41880 | D20: Stapler | E20: 12 | G20: Electronic | H20: 15985
A21: Online | B21: 22567 | D21: Whiteboard Marker | E21: 9 | G21: Grand Total | H21: 347436
A22: Online | B22: 19474 | D22: Study Table | E22: 9
A23: Unknown | B23: 12986 | D23: Power Bank | E23: 9
A24: Upi | B24: 56778 | D24: Headphones | E24: 7
A25: Grand Total | B25: 347436 | D25: Webcam | E25: 6
D26: File Folder | E26: 5
D27: Wireless Mouse | E27: 5
D28: Toor Dal 1kg | E28: 5
D29: Sports Shorts | E29: 3
D30: Sticky Notes | E30: 3
D31: Notebook Pack | E31: 2
D32: Cotton T-Shirt | E32: 1
D33: Grand Total | E33: 464
B80: Values
B81: Average of Quantity | C81: Count of Customer Name | D81: Sum of Sales Amount | E81: Count of Product
A82: Total | B82: 6.6285714 | C82: 70 | D82: 347436 | E82: 70

Sheet Sheet9
A1: Order ID | B1: Order Date | C1: Customer Name | D1: Region | E1: Category | F1: Product | G1: Quantity | H1: Unit Price | I1: Sales Amount | J1: Payment Method | K1: Notes
A2: 1084 | B2: 45436 | C2: Sanjay Chauhan | D2: East | E2: Furniture | F2: Filing Cabinet | G2: 10 | H2: 1499 | I2: =G2*H2 -> 14990 | J2: Debit Card | K2: Not Available
A3: 1135 | B3: 45340 | C3: Ajay Verma | D3: North | E3: Furniture | F3: Bed Frame | G3: 7 | H3: 799 | I3: =G3*H3 -> 5593 | J3: Cash | K3: Not Available
A4: 1013 | B4: 45497 | C4: Divya Gupta | D4: North | E4: Furniture | F4: Bed Frame | G4: 8 | H4: 1999 | I4: =G4*H4 -> 15992 | J4: Cash | K4: Not Available
A5: 1116 | B5: 45582 | C5: Tanvi Kapoor | D5: West | E5: Stationaries | F5: Gel Pens (10) | G5: 1 | H5: 799 | I5: =G5*H5 -> 799 | J5: Credit Card | K5: Not Available
A6: 1044 | B6: 45583 | C6: Swati Pandey | D6: South | E6: Furniture | F6: Office Chair | G6: 3 | H6: 699 | I6: =G6*H6 -> 2097 | J6: Upi | K6: Not Available
A7: 1118 | B7: 45619 | C7: Ravi Kumar | D7: East | E7: Groceries | F7: Sugar 1kg | G7: 12 | H7: 699 | I7: =G7*H7 -> 8388 | J7: Card | K7: Not Available
A8: 1025 | B8: 45631 | C8: Karan Mukherjee | D8: South | E8: Groceries | F8: Sunflower Oil 1L | G8: 11 | H8: 199 | I8: =G8*H8 -> 2189 | J8: Online | K8: Not Available
A9: 1133 | B9: 45649 | C9: Deepa Chauhan | D9: West | E9: Electronics | F9: LED Bulb | G9: 9 | H9: 699 | I9: =G9*H9 -> 6291 | J9: Upi | K9: Not Available
A10: 1005 | B10: 45635 | C10: Simran Bose | D10: North | E10: Groceries | F10: Basmati Rice 5kg | G10: 4 | H10: 799 | I10: =G10*H10 -> 3196 | J10: Online | K10: Not Available
A11: 1083 | B11: 45314 | C11: Nikhil Bose | D11: South | E11: Groceries | F11: Sunflower Oil 1L | G11: 3 | H11: 349 | I11: =G11*H11 -> 1047 | J11: Card | K11: Not Available
A12: 1100 | B12: 45589 | C12: Sneha Gupta | D12: East | E12: Apparel | F12: Woolen Sweater | G12: 11 | H12: 349 | I12: =G12*H12 -> 3839 | J12: Cash | K12: Not Available
A13: 1138 | B13: 45637 | C13: Nikhil Pillai | D13: East | E13: Groceries | F13: Sunflower Oil 1L | G13: 11 | H13: 999 | I13: =G13*H13 -> 10989 | J13: Credit Card | K13: Returned
... A32: 1087 | B32: 45368 | C32: Anjali Singh | D32: West | E32: Apparel | F32: Cotton T-Shirt | G32: 1 | H32: 599 | I32: =G32*H32 -> 599 | J32: Online | K32: Returned
A33: 1094 | B33: 45603 | C33: Pooja Kumar | D33: =D32 -> West | E33: Apparel | F33: Sports Shorts | G33: 3 | H33: 99 | I33: =G33*H33 -> 297 | J33: Upi | K33: Not Available
A34: 1105 | B34: 45497 | C34: Kavya Chauhan | D34: North | E34: Furniture | F34: Filing Cabinet | G34: 6 | H34: 999 | I34: =G34*H34 -> 5994 | J34: Online | K34: Not Available
A35: 1058 | B35: 45498 | C35: Ajay Reddy | D35: South | E35: Electronic | F35: USB Cable | G35: 5 | H35: 1499 | I35: =G35*H35 -> 7495 | J35: Cash | K35: Not Available
A36: 1045 | B36: 45608 | C36: Vivek Chatterjee | D36: North | E36: Stationaries | F36: Sticky Notes | G36: 1 | H36: 199 | I36: =G36*H36 -> 199 | J36: Online | K36: Not Available
A37: 1024 | B37: 45357 | C37: Meera Singh | D37: South | E37: Groceries | F37: Green Tea Pack | G37: 11 | H37: 349 | I37: =G37*H37 -> 3839 | J37: Debit Card | K37: Not Available
A38: 1109 | B38: 45396 | C38: Nikhil Chatterjee | D38: North | E38: Electronics | F38: Headphones | G38: 7 | H38: 299 | I38: =G38*H38 -> 2093 | J38: Debit Card | K38: Not Available
A39: 1143 | B39: 45630 | C39: Amit Pillai | D39: South | E39: Groceries | F39: Green Tea Pack | G39: 6 | H39: 249 | I39: =G39*H39 -> 1494 | J39: Debit Card | K39: Not Available
A40: 1085 | B40: 45431 | C40: Gaurav Reddy | D40: East | E40: Electronic | F40: Wireless Mouse | G40: 5 | H40: 199 | I40: =G40*H40 -> 995 | J40: Debit Card | K40: Not Available
A41: 1093 | B41: 45519 | C41: Suresh Mukherjee | D41: North | E41: Stationaries | F41: Stapler | G41: 10 | H41: 1199 | I41: =G41*H41 -> 11990 | J41: Unknown | K41: Not Available
A42: 1125 | B42: 45365 | C42: Sanjay Rao | D42: East | E42: Apparel | F42: Woolen Sweater | G42: 10 | H42: 799 | I42: =G42*H42 -> 7990 | J42: Debit Card | K42: Not Available
A43: 1146 | B43: 45636 | C43: Anjali Pandey | D43: West | E43: Electronics | F43: LED Bulb | G43: 4 | H43: 2499 | I43: =G43*H43 -> 9996 | J43: Online | K43: Not Available
A44: 1074 | B44: 45586 | C44: Amit Bose | D44: North | E44: Electronics | F44: USB Cable | G44: 8 | H44: 199 | I44: =G44*H44 -> 1592 | J44: Online | K44: Not Available
A45: 1046 | B45: 45532 | C45: Ritu Kumar | D45: West | E45: Furniture | F45: Bed Frame | G45: 11 | H45: 1999 | I45: =G45*H45 -> 21989 | J45: Upi | K45: Not Available
... A47: 1001 | B47: 45393 | C47: Ajay Nair | D47: North | E47: Groceries | F47: Basmati Rice 5kg | G47: 2 | H47: 399 | I47: =G47*H47 -> 798 | J47: Debit Card | K47: Not Available
A48: 1058 | B48: =B40 -> 45431 | C48: Ajay Reddy | D48: South | E48: Electronic | F48: USB Cable | G48: 5 | H48: 1499 | I48: =G48*H48 -> 7495 | J48: Cash | K48: Not Available
A49: 1012 | B49: 45301 | C49: Neha Mukherjee | D49: North | E49: Groceries | F49: Wheat Flour 5kg | G49: 2 | H49: 499 | I49: =G49*H49 -> 998 | J49: Cash | K49: Not Available
A50: 1151 | B50: 45599 | C50: Sneha Chauhan | D50: North | E50: Stationaries | F50: Gel Pens (10) | G50: 9 | H50: 999 | I50: =G50*H50 -> 8991 | J50: Upi | K50: Not Available
A51: 1117 | B51: 45520 | C51: Harsh Chatterjee | D51: South | E51: Groceries | F51: Sunflower Oil 1L | G51: 1 | H51: 599 | I51: =G51*H51 -> 599 | J51: Card | K51: Not Available
A52: 1048 | B52: 45421 | C52: Pooja Verma | D52: North | E52: Stationaries | F52: Gel Pens (10) | G52: 5 | H52: 1499 | I52: =G52*H52 -> 7495 | J52: Cash | K52: Not Available
A53: 1158 | B53: 45457 | C53: Manoj Sharma | D53: East | E53: Apparel | F53: Formal Shirt | G53: 7 | H53: 399 | I53: =G53*H53 -> 2793 | J53: Card | K53: Cancelled
A54: 1139 | B54: 45336 | C54: Arjun Chatterjee | D54: North | E54: Electronics | F54: Webcam | G54: 6 | H54: 599 | I54: =G54*H54 -> 3594 | J54: Upi | K54: Not Available
A55: 1063 | B55: 45400 | C55: Divya Das | D55: East | E55: Groceries | F55: Sunflower Oil 1L | G55: 2 | H55: 1499 | I55: =G55*H55 -> 2998 | J55: Online | K55: Returned
A56: 1153 | B56: 45526 | C56: Kavya Mukherjee | D56: South | E56: Electronics | F56: Power Bank | G56: 9 | H56: 699 | I56: =G56*H56 -> 6291 | J56: Upi | K56: Returned
A57: 1107 | B57: 45551 | C57: Anjali Iyer | D57: South | E57: Apparel | F57: Formal Shirt | G57: 7 | H57: 699 | I57: =G57*H57 -> 4893 | J57: Debit Card | K57: Not Available
A58: 1030 | B58: 45453 | C58: Gaurav Mukherjee | D58: West | E58: Electronics | F58: LED Bulb | G58: 7 | H58: 1199 | I58: =G58*H58 -> 8393 | J58: Credit Card | K58: Not Available
A59: 1144 | B59: 45370 | C59: Ravi Joshi | D59: North | E59: Groceries | F59: Toor Dal 1kg | G59: 5 | H59: 499 | I59: =G59*H59 -> 2495 | J59: Upi | K59: Returned
A60: 1092 | B60: 45480 | C60: Tanvi Verma | D60: West | E60: Groceries | F60: Wheat Flour 5kg | G60: 3 | H60: 1999 | I60: =G60*H60 -> 5997 | J60: Credit Card | K60: Not Available
A61: 1060 | B61: 45618 | C61: Ritu Chatterjee | D61: North | E61: Apparel | F61: Kurta Set | G61: 6 | H61: 599 | I61: =G61*H61 -> 3594 | J61: Cash | K61: Not Available
A62: 1091 | B62: 45422 | C62: Priya Iyer | D62: North | E62: =E58 -> Electronics | F62: LED Bulb | G62: 9 | H62: 999 | I62: =G62*H62 -> 8991 | J62: Credit Card | K62: Not Available
A63: 1016 | B63: 45580 | C63: Rohit Pillai | D63: West | E63: Stationaries | F63: Sticky Notes | G63: 2 | H63: 99 | I63: =G63*H63 -> 198 | J63: Cash | K63: Not Available
A64: 1004 | B64: 45379 | C64: Suresh Rao | D64: South | E64: Stationaries | F64: File Folder | G64: 5 | H64: 199 | I64: =G64*H64 -> 995 | J64: Credit Card | K64: Not Available
A65: 1119 | B65: =B68 -> 45532 | C65: Arjun Malhotra | D65: =D64 -> South | E65: Furniture | F65: Filing Cabinet | G65: 10 | H65: 199 | I65: =G65*H65 -> 1990 | J65: Card | K65: Returned
A66: 1150 | B66: 45526 | C66: Priya Das | D66: East | E66: Groceries | F66: Green Tea Pack | G66: 10 | H66: 249 | I66: =G66*H66 -> 2490 | J66: Cash | K66: Not Available
A67: 1075 | B67: 45497 | C67: Sneha Nair | D67: West | E67: Stationaries | F67: Stapler | G67: 2 | H67: 499 | I67: =G67*H67 -> 998 | J67: Cash | K67: Not Available
A68: 1089 | B68: 45532 | C68: Neha Rao | D68: East | E68: Apparel | F68: Woolen Sweater | G68: 9 | H68: 99 | I68: =G68*H68 -> 891 | J68: Online | K68: Not Available
A69: 1042 | B69: 45398 | C69: Rohit Chatterjee | D69: East | E69: Apparel | F69: Woolen Sweater | G69: 12 | H69: 249 | I69: =G69*H69 -> 2988 | J69: Credit Card | K69: Returned
A70: 1079 | B70: 45335 | C70: Isha Verma | D70: West | E70: Furniture | F70: Bed Frame | G70: 2 | H70: 799 | I70: =G70*H70 -> 1598 | J70: Online | K70: Not Available
A71: 1134 | B71: 45648 | C71: Meera Nair | D71: East | E71: Groceries | F71: Wheat Flour 5kg | G71: 7 | H71: 1499 | I71: =G71*H71 -> 10493 | J71: Credit Card | K71: Not Available

Sheet Sheet11

Sheet DASHBOARD
F6: AVG QTY | H6: SUM OF AMOUNT | J6: COUNT OF PRODUCT | L6: COUNT OF CUSTOMER
F7: =SUM(GETPIVOTDATA("Average of Quantity",Sheet8!$A$80)) -> 6.6285714 | H7: =SUM(GETPIVOTDATA("Sum of Sales Amount",Sheet8!$A$80)) -> 347436 | J7: =SUM(GETPIVOTDATA("Count of Product",Sheet8!$A$80)) -> 70 | L7: =SUM(GETPIVOTDATA("Count of Customer Name",Sheet8!$A$80)) -> 70

Sheet Sheet16
A3: Sum of Sales Amount | B3: Average of Customer Rating | C3: Count of Order ID | D3: Average of Sales Amount2 | E3: Sum of Quantity | F3: Sum of Profit
A4: 21157326 | B4: 2.979 | C4: 1000 | D4: 21157.326 | E4: 3066 | F4: 3947701.8

Sheet Sheet15
G8: TOTAL SALES | I8: AVG RATING | K8: AVG SALES | M8: TOTAL ORDERS | O8: TOTAL QTY SOLD | Q8: TOTAL PROFIT
G9: =SUM(GETPIVOTDATA("Sum of Sales Amount",Sheet16!$A$3)) -> 21157326 | I9: =SUM(GETPIVOTDATA("Average of Customer Rating",Sheet16!$A$3)) -> 2.979 | K9: =SUM(GETPIVOTDATA("Average of Sales Amount2",Sheet16!$A$3)) -> 21157.326 | M9: =SUM(GETPIVOTDATA("Count of Order ID",Sheet16!$A$3)) -> 1000 | O9: =SUM(GETPIVOTDATA("Sum of Quantity",Sheet16!$A$3)) -> 3066 | Q9: =SUM(GETPIVOTDATA("Sum of Profit",Sheet16!$A$3)) -> 3947701.8

Sheet Sheet12
A1: Order ID | B1: Order Date | C1: Customer ID | D1: Customer Name | E1: Product | F1: Category | G1: Brand | H1: Quantity | I1: Unit Price | J1: Discount | K1: Sales Amount | L1: Profit | M1: Payment Method | N1: City | O1: State | P1: Salesperson | Q1: Delivery Status | R1: Customer Rating
A2: O00001 | B2: 45862 | C2: C00001 | D2: Customer 1 | E2: Watch | F2: Accessories | G2: Fossil | H2: 5 | I2: 6059 | J2: 0 | K2: 30295 | L2: 3949.04 | M2: Card | N2: Hyderabad | O2: Telangana | P2: Anil | Q2: Shipped | R2: 3
A3: O00002 | B3: 45762 | C3: C00002 | D3: Customer 2 | E3: Watch | F3: Accessories | G3: Fossil | H3: 5 | I3: 3639 | J3: 0 | K3: 18195 | L3: 5181.43 | M3: Card | N3: Chennai | O3: Tamil Nadu | P3: Anil | Q3: Delivered | R3: 4
A4: O00003 | B4: 45983 | C4: C00003 | D4: Customer 3 | E4: Book | F4: Books | G4: Penguin | H4: 4 | I4: 2520 | J4: 0 | K4: 10080 | L4: 2867.57 | M4: Net Banking | N4: Chennai | O4: Tamil Nadu | P4: Asha | Q4: Cancelled | R4: 4
A5: O00004 | B5: 45718 | C5: C00004 | D5: Customer 4 | E5: Shoes | F5: Fashion | G5: Nike | H5: 1 | I5: 10604 | J5: 0.15 | K5: 9013.4 | L5: 862.52 | M5: Net Banking | N5: Bengaluru | O5: Karnataka | P5: John | Q5: Delivered | R5: 4
A6: O00005 | B6: 45721 | C6: C00005 | D6: Customer 5 | E6: Book | F6: Books | G6: Penguin | H6: 3 | I6: 14673 | J6: 0 | K6: 44019 | L6: 12200.93 | M6: Net Banking | N6: Chennai | O6: Tamil Nadu | P6: Rahul | Q6: Returned | R6: 2
A7: O00006 | B7: 45731 | C7: C00006 | D7: Customer 6 | E7: Phone | F7: Electronics | G7: Samsung | H7: 1 | I7: 8627 | J7: 0.1 | K7: 7764.3 | L7: 2271.81 | M7: Net Banking | N7: Bengaluru | O7: Karnataka | P7: Anil | Q7: Cancelled | R7: 3
A8: O00007 | B8: 45977 | C8: C00007 | D8: Customer 7 | E8: Headphones | F8: Electronics | G8: Sony | H8: 3 | I8: 5419 | J8: 0.15 | K8: 13818.45 | L8: 1723.83 | M8: UPI | N8: Kochi | O8: Kerala | P8: Asha | Q8: Cancelled | R8: 1
A9: O00008 | B9: 45806 | C9: C00008 | D9: Customer 8 | E9: Laptop | F9: Electronics | G9: Dell | H9: 1 | I9: 6879 | J9: 0.15 | K9: 5847.15 | L9: 953.22 | M9: Wallet | N9: Kochi | O9: Kerala | P9: John | Q9: Shipped | R9: 5
A10: O00009 | B10: 45746 | C10: C00009 | D10: Customer 9 | E10: Headphones | F10: Electronics | G10: Sony | H10: 4 | I10: 10033 | J10: 0.05 | K10: 38125.4 | L10: 8831.79 | M10: Net Banking | N10: Bengaluru | O10: Karnataka | P10: Priya | Q10: Cancelled | R10: 2
A11: O00010 | B11: 45724 | C11: C00010 | D11: Customer 10 | E11: Headphones | F11: Electronics | G11: Sony | H11: 1 | I11: 2263 | J11: 0.1 | K11: 2036.7 | L11: 606.39 | M11: Card | N11: Delhi | O11: Delhi | P11: Rahul | Q11: Shipped | R11: 4
A12: O00011 | B12: 45861 | C12: C00011 | D12: Customer 11 | E12: Watch | F12: Accessories | G12: Fossil | H12: 1 | I12: 10944 | J12: 0.05 | K12: 10396.8 | L12: 3040.08 | M12: Wallet | N12: Hyderabad | O12: Telangana | P12: Priya | Q12: Cancelled | R12: 5
A13: O00012 | B13: 45834 | C13: C00012 | D13: Customer 12 | E13: Mixer | F13: Home | G13: Philips | H13: 2 | I13: 10645 | J13: 0.2 | K13: 17032 | L13: 3795.71 | M13: Card | N13: Mumbai | O13: Maharashtra | P13: Asha | Q13: Returned | R13: 1
... A1001: O01000 | B1001: 45787 | C1001: C01000 | D1001: Customer 1000 | E1001: Shoes | F1001: Fashion | G1001: Nike | H1001: 5 | I1001: 5977 | J1001: 0.15 | K1001: 25402.25 | L1001: 5802.19 | M1001: COD | N1001: Hyderabad | O1001: Telangana | P1001: Rahul | Q1001: Cancelled | R1001: 3

Sheet Sheet14
A3: Row Labels | B3: Count of Match ID | D3: Row Labels | E3: Sum of Home Goals | G3: Row Labels | H3: Count of Match ID | J3: Count of Match ID | K3: Column Labels
A4: Bundesliga | B4: 55 | D4: Ac Milan | E4: 28 | G4: A | H4: 200 | J4: Row Labels | K4: A | L4: D | M4: H | N4: Unknown | O4: Grand Total
A5: La Liga | B5: 114 | D5: Ajax | E5: 26 | G5: D | H5: 134 | J5: Ac Milan | K5: 7 | L5: 5 | M5: 7 | O5: 19
A6: Ligue 1 | B6: 125 | D6: Arsenal | E6: 64 | G6: H | H6: 254 | J6: Ajax | K6: 3 | L6: 4 | M6: 4 | N6: 1 | O6: 12
A7: Premier League | B7: 177 | D7: Atletico Madrid | E7: 56 | G7: Unknown | H7: 12 | J7: Arsenal | K7: 5 | L7: 8 | M7: 17 | N7: 3 | O7: 33
A8: Serie A | B8: 117 | D8: Barcelona | E8: 71 | G8: Grand Total | H8: 600 | J8: Atletico Madrid | K8: 4 | L8: 12 | M8: 10 | N8: 1 | O8: 27
A9: Unknown | B9: 12 | D9: Bayern Munich | E9: 59 | J9: Barcelona | K9: 14 | L9: 9 | M9: 13 | O9: 36
A10: Grand Total | B10: 600 | D10: Benfica | E10: 37 | G10: Row Labels | H10: Average of Attendance | J10: Bayern Munich | K10: 8 | L10: 9 | M10: 17 | O10: 34
D11: Borussia Dortmund | E11: 50 | G11: Bundesliga | H11: 43595.636 | J11: Benfica | K11: 9 | L11: 3 | M11: 7 | N11: 4 | O11: 23
D12: Chelsea | E12: 73 | G12: La Liga | H12: 43255.175 | J12: Borussia Dortmund | K12: 9 | L12: 9 | M12: 10 | O12: 28
D13: Inter Milan | E13: 29 | G13: Ligue 1 | H13: 41289.88 | J13: Chelsea | K13: 15 | L13: 7 | M13: 19 | O13: 41
D14: Juventus | E14: 35 | G14: Premier League | H14: 45113.379 | J14: Inter Milan | K14: 5 | L14: 3 | M14: 6 | O14: 14
D15: Liverpool | E15: 94 | G15: Serie A | H15: 48088.795 | J15: Juventus | K15: 7 | L15: 3 | M15: 8 | O15: 18
D16: Manchester City | E16: 50 | G16: Unknown | H16: 52824.417 | J16: Liverpool | K16: 19 | L16: 9 | M16: 21 | O16: 49
D17: Manchester United | E17: 111 | G17: Grand Total | H17: 44559.058 | J17: Manchester City | K17: 14 | L17: 6 | M17: 12 | N17: 3 | O17: 35
D18: Newcastle United | E18: 102 | J18: Manchester United | K18: 24 | L18: 11 | M18: 27 | O18: 62
D19: Paris Saint-Germain | E19: 48 | G19: Row Labels | H19: Sum of Home Goals | J19: Newcastle United | K19: 14 | L19: 12 | M19: 25 | O19: 51
D20: Real Madrid | E20: 86 | G20: 2022/23 | H20: 184 | J20: Paris Saint-Germain | K20: 11 | L20: 6 | M20: 10 | O20: 27
D21: Tottenham Hotspur | E21: 88 | G21: 2023/24 | H21: 190 | J21: Real Madrid | K21: 11 | L21: 10 | M21: 20 | O21: 41
D22: Unknown | E22: 12 | G22: 2024/25 | H22: 173 | J22: Tottenham Hotspur | K22: 17 | L22: 7 | M22: 19 | O22: 43
D23: Grand Total | E23: 1119 | G23: 2025/26 | H23: 339 | J23: Unknown | K23: 4 | L23: 1 | M23: 2 | O23: 7
G24: Unknown | H24: 233 | J24: Grand Total | K24: 200 | L24: 134 | M24: 254 | N24: 12 | O24: 600
G25: Grand Total | H25: 1119

Sheet Sheet18
A3: Count of Match ID | B3: Average of Attendance | C3: Sum of Away Goals | D3: Sum of Home Goals
A4: 600 | B4: 44559.058 | C4: 1035 | D4: 1119

Sheet project
A1: Match ID | B1: Match Date | C1: League | D1: Home Team | E1: Away Team | F1: Home Goals | G1: Away Goals | H1: Full-Time Result | I1: Attendance | J1: Stadium | K1: Referee | L1: Season
A2: M1253 | B2: 44780 | C2: Premier League | D2: Chelsea | E2: Ac Milan | F2: 3 | G2: 2 | H2: H | I2: 64034 | J2: Tottenham Hotspur Stadium | K2: Anthony Taylor | L2: 2025/26
A3: M1439 | B3: 44782 | C3: Bundesliga | D3: Manchester United | E3: Bayern Munich | F3: 2 | G3: 1 | H3: H | I3: 49406 | J3: Emirates Stadium | K3: Anthony Taylor | L3: 2025/26
A4: M1277 | B4: 44787 | C4: La Liga | D4: Manchester United | E4: Juventus | F4: 1 | G4: 3 | H4: A | I4: 17408 | J4: San Siro | K4: Michael Oliver | L4: 2022/23
A5: M1575 | B5: 44788 | C5: Ligue 1 | D5: Chelsea | E5: Inter Milan | F5: 2 | G5: 1 | H5: H | I5: 0 | J5: St James' Park | K5: A. Taylor | L5: 2023/24
A6: M1154 | B6: 44789 | C6: Premier League | D6: Manchester City | E6: Liverpool | F6: 2 | G6: 1 | H6: H | I6: 58334 | J6: Camp Nou | K6: A. Taylor | L6: 2025/26
A7: M1580 | B7: 44790 | C7: Serie A | D7: Borussia Dortmund | E7: Newcastle United | F7: 1 | G7: 0 | H7: H | I7: 36967 | J7: Tottenham Hotspur Stadium | K7: Daniele Orsato | L7: 2024/25
A8: M1553 | B8: 44791 | C8: Ligue 1 | D8: Manchester City | E8: Borussia Dortmund | F8: 0 | G8: 1 | H8: A | I8: 21705 | J8: Tottenham Hotspur Stadium | K8: S. Marciniak | L8: 2025/26
A9: M1587 | B9: 44792 | C9: Serie A | D9: Inter Milan | E9: Chelsea | F9: 5 | G9: 2 | H9: H | I9: 28815 | J9: Tottenham Hotspur Stadium | K9: Unknown | L9: 2023/24
A10: M1363 | B10: 44793 | C10: Serie A | D10: Tottenham Hotspur | E10: Bayern Munich | F10: 4 | G10: 0 | H10: H | I10: 48806 | J10: Anfield | K10: A. Taylor | L10: 2025/26
A11: M1511 | B11: 44795 | C11: Ligue 1 | D11: Tottenham Hotspur | E11: Real Madrid | F11: 2 | G11: 3 | H11: A | I11: 30237 | J11: Parc des Princes | K11: Unknown | L11: 2023/24
A12: M1573 | B12: 44795 | C12: Premier League | D12: Liverpool | E12: Manchester City | F12: 0 | G12: 3 | H12: A | I12: 53573 | J12: Etihad Stadium | K12: Unknown | L12: 2025/26
A13: M1353 | B13: 44797 | C13: Ligue 1 | D13: Liverpool | E13: Borussia Dortmund | F13: 1 | G13: 4 | H13: A | I13: 76293 | J13: Parc des Princes | K13: C. Pawson | L13: 2023/24
... A20: M1001 | B20: 44825 | C20: Premier League | D20: Bayern Munich | E20: Liverpool | F20: 3 | G20: 1 | H20: H | I20: 21934 | J20: Signal Iduna Park | K20: Unknown | L20: 2022/23
A21: M1477 | B21: 44825 | C21: Premier League | D21: Real Madrid | F21: 1 | G21: 0 | H21: H | I21: 34701 | J21: Etihad Stadium | K21: Michael Oliver | L21: 2024/25
A22: M1071 | B22: 44826 | C22: Serie A | D22: Liverpool | E22: Barcelona | F22: 4 | G22: 2 | H22: H | I22: 60490 | J22: San Siro | K22: A. Taylor | L22: 2022/23
A23: M1428 | B23: 44826 | C23: La Liga | D23: Liverpool | E23: Borussia Dortmund | F23: 2 | G23: 6 | H23: A | I23: 63362 | J23: St James' Park | K23: Unknown | L23: Unknown
A24: M1199 | B24: 44827 | C24: Serie A | D24: Benfica | E24: Liverpool | F24: 2 | G24: 1 | H24: H | I24: 23935 | J24: Etihad Stadium | K24: C. Pawson | L24: Unknown
A25: M1179 | B25: 44828 | C25: Bundesliga | D25: Paris Saint-Germain | E25: Tottenham Hotspur | F25: 1 | G25: 1 | H25: D | I25: 39403 | J25: St James' Park | K25: Anthony Taylor | L25: 2024/25
A26: M1210 | B26: 44832 | C26: Ligue 1 | D26: Manchester United | E26: Ac Milan | F26: 0 | G26: 4 | H26: A | I26: 43188 | J26: Signal Iduna Park | K26: A. Taylor | L26: 2025/26
A27: M1196 | B27: 44837 | C27: Serie A | D27: Bayern Munich | E27: Arsenal | F27: 0 | G27: 2 | H27: A | I27: 13061 | J27: Emirates Stadium | K27: Anthony Taylor | L27: 2023/24
A28: M1023 | B28: 44838 | C28: La Liga | D28: Manchester United | E28: Paris Saint-Germain | F28: 3 | G28: 0 | H28: H | I28: 0 | J28: Signal Iduna Park | K28: Unknown | L28: 2023/24
A29: M1002 | B29: 44839 | C29: Ligue 1 | D29: Barcelona | E29: Newcastle United | F29: 0 | G29: 1 | H29: A | I29: 11978 | J29: Camp Nou | K29: A. Taylor | L29: Unknown
A30: M1010 | B30: 44839 | C30: Premier League | D30: Chelsea | E30: Ac Milan | F30: 3 | G30: 1 | H30: H | I30: 36153 | J30: Allianz Arena | K30: S. Marciniak | L30: 2023/24
A31: M1509 | B31: 44849 | C31: Ligue 1 | D31: Arsenal | E31: Ajax | F31: 2 | G31: 2 | H31: D | I31: 70379 | J31: Signal Iduna Park | K31: Michael Oliver | L31: 2024/25
A32: M1166 | B32: 44854 | C32: Serie A | D32: Bayern Munich | E32: Arsenal | F32: 1 | G32: 1 | H32: D | I32: 77190 | J32: Camp Nou | K32: Michael Oliver | L32: 2024/25
A33: M1600 | B33: 44857 | C33: Premier League | D33: Chelsea | E33: Real Madrid | F33: 2 | G33: 3 | H33: A | I33: 36798 | J33: Camp Nou | K33: Anthony Taylor | L33: 2022/23
... A593: M1434 | B593: 46168 | C593: Premier League | D593: Liverpool | E593: Paris Saint-Germain | F593: 1 | G593: 1 | H593: D | I593: 28262 | J593: Emirates Stadium | K593: A. Taylor | L593: 2024/25
A594: M1015 | C594: Serie A | D594: Juventus | E594: Bayern Munich | F594: 0 | G594: 1 | H594: A | I594: 8925 | J594: San Siro | K594: C. Pawson | L594: 2025/26
A595: M1114 | C595: La Liga | D595: Inter Milan | E595: Manchester United | F595: 1 | G595: 1 | H595: D | I595: 78121 | J595: St James' Park | K595: Michael Oliver | L595: 2023/24
A596: M1152 | C596: La Liga | D596: Chelsea | E596: Arsenal | F596: 0 | G596: 1 | H596: A | I596: 72283 | J596: Camp Nou | K596: C. Pawson | L596: 2022/23
A597: M1295 | C597: Serie A | D597: Paris Saint-Germain | E597: Barcelona | F597: 2 | G597: 0 | H597: H | I597: 30716 | J597: Emirates Stadium | K597: C. Pawson | L597: 2024/25
A598: M1313 | C598: Ligue 1 | D598: Arsenal | E598: Bayern Munich | F598: 1 | G598: 0 | H598: H | I598: 0 | J598: Santiago Bernabéu | K598: Daniele Orsato | L598: 2025/26
A599: M1352 | C599: La Liga | D599: Ajax | E599: Newcastle United | F599: 1 | G599: 2 | H599: A | I599: 31522 | J599: Anfield | K599: M. Oliver | L599: Unknown
A600: M1461 | C600: Bundesliga | D600: Paris Saint-Germain | E600: Arsenal | F600: 3 | G600: 1 | H600: H | I600: 44958 | J600: Old Trafford | K600: Unknown | L600: 2023/24
A601: M1483 | C601: Premier League | D601: Manchester United | E601: Arsenal | F601: 2 | G601: 0 | H601: H | I601: 64665 | J601: Etihad Stadium | K601: Unknown | L601: 2024/25

Sheet  45
F6: TOTAL MATCHES | J6: AVG ATTENDENCE | N6: HOME GOALS | R6: AWAY GOALS
F7: =SUM(GETPIVOTDATA("Match ID",Sheet18!$A$3)) -> 600 | J7: =SUM(GETPIVOTDATA("Average of Attendance",Sheet18!$A$3)) -> 44559.058 | N7: =SUM(GETPIVOTDATA("Sum of Away Goals",Sheet18!$A$3)) -> 1035 | R7: =SUM(GETPIVOTDATA("Sum of Home Goals",Sheet18!$A$3)) -> 1119

Sheet macro
A1: employe | B1: Email Address | C1: Full Address | D1: Username (Q2) | E1: Domain (Q4) | F1: City (Q6)
A2: Nikhil Rane | B2: nikhil.rane@gmail.com | C2: 204, MG Road, Pune, 411001 | D2: nikhil.rane | E2: =RIGHT(B2,LEN(B2)-FIND("@",B2)) -> gmail.com | F2: PUNE
A3: Sarah MATHEW | B3: sarah.mathew@OUTLOOK.com | C3: 12, Park Street, Kolkata, 700016 | D3: sarah.mathew | E3: =RIGHT(B3,LEN(B3)-FIND("@",B3)) -> OUTLOOK.com | F3: .
A4: Farhan Sheikh | B4: farhan.s@yahoo.co.in | C4: 45, Anna Salai, Chennai, 600002 | D4: farhan.s | E4: =RIGHT(B4,LEN(B4)-FIND("@",B4)) -> yahoo.co.in | F4: CHENNAI
A5: Divya Krishnan | B5: divya.k@gmail.com | C5: 7, Residency Road, Bengaluru, 560025 | D5: divya.k | E5: =RIGHT(B5,LEN(B5)-FIND("@",B5)) -> gmail.com | F5: BENGALURU
A6: Om Prakash | B6: om.prakash@COMPANYMAIL.com | C6: 19, Civil Lines, Nagpur, 440001 | D6: om.prakash | E6: =RIGHT(B6,LEN(B6)-FIND("@",B6)) -> COMPANYMAIL.com | F6: NAGPUR
A7: Leena D'Souza | B7: leena.ds@gmail.com | C7: 88, Linking Road, Mumbai, 400050 | D7: leena.ds | E7: =RIGHT(B7,LEN(B7)-FIND("@",B7)) -> gmail.com | F7: MUMBAI
